{
"meta":{"test_sets":[],"test_metrics":[],"learn_metrics":[{"best_value":"Min","name":"RMSE"}],"launch_mode":"Train","parameters":"","iteration_count":1000,"learn_sets":["learn"],"name":"experiment"},
"iterations":[
{"learn":[14.61268541],"iteration":0,"passed_time":0.1573672146,"remaining_time":157.2098474},
{"learn":[14.23196558],"iteration":1,"passed_time":0.1581295566,"remaining_time":78.90664873},
{"learn":[13.86674177],"iteration":2,"passed_time":0.1587893522,"remaining_time":52.77099471},
{"learn":[13.49946468],"iteration":3,"passed_time":0.1593811567,"remaining_time":39.68590801},
{"learn":[13.16661202],"iteration":4,"passed_time":0.1600303634,"remaining_time":31.84604233},
{"learn":[12.85632158],"iteration":5,"passed_time":0.1606223094,"remaining_time":26.60976259},
{"learn":[12.56784336],"iteration":6,"passed_time":0.1611905319,"remaining_time":22.8660283},
{"learn":[12.31617801],"iteration":7,"passed_time":0.1617712766,"remaining_time":20.0596383},
{"learn":[12.01509946],"iteration":8,"passed_time":0.1623726697,"remaining_time":17.87903508},
{"learn":[11.71512571],"iteration":9,"passed_time":0.1628635944,"remaining_time":16.12349585},
{"learn":[11.43264457],"iteration":10,"passed_time":0.1635436862,"remaining_time":14.70406415},
{"learn":[11.17973129],"iteration":11,"passed_time":0.164089629,"remaining_time":13.51004612},
{"learn":[10.93746433],"iteration":12,"passed_time":0.1646903409,"remaining_time":12.50379742},
{"learn":[10.69387075],"iteration":13,"passed_time":0.1652638127,"remaining_time":11.63929424},
{"learn":[10.4615922],"iteration":14,"passed_time":0.1659086605,"remaining_time":10.8946687},
{"learn":[10.2299235],"iteration":15,"passed_time":0.1665235561,"remaining_time":10.2411987},
{"learn":[10.01419731],"iteration":16,"passed_time":0.1671037599,"remaining_time":9.662529176},
{"learn":[9.795856918],"iteration":17,"passed_time":0.1676078782,"remaining_time":9.143940908},
{"learn":[9.60040151],"iteration":18,"passed_time":0.1683611519,"remaining_time":8.692752104},
{"learn":[9.418664989],"iteration":19,"passed_time":0.1691045073,"remaining_time":8.286120857},
{"learn":[9.249278645],"iteration":20,"passed_time":0.1697708649,"remaining_time":7.914556035},
{"learn":[9.090113396],"iteration":21,"passed_time":0.17037424,"remaining_time":7.573909397},
{"learn":[8.909548708],"iteration":22,"passed_time":0.1710149228,"remaining_time":7.264416503},
{"learn":[8.740140208],"iteration":23,"passed_time":0.1718026263,"remaining_time":6.986640137},
{"learn":[8.59377682],"iteration":24,"passed_time":0.1724720485,"remaining_time":6.726409892},
{"learn":[8.453885414],"iteration":25,"passed_time":0.173085613,"remaining_time":6.484053347},
{"learn":[8.317732234],"iteration":26,"passed_time":0.1736381329,"remaining_time":6.257403827},
{"learn":[8.180896085],"iteration":27,"passed_time":0.1741980825,"remaining_time":6.047162005},
{"learn":[8.053220863],"iteration":28,"passed_time":0.1747911996,"remaining_time":5.852491544},
{"learn":[7.924234474],"iteration":29,"passed_time":0.1755003932,"remaining_time":5.674512714},
{"learn":[7.818879511],"iteration":30,"passed_time":0.1760818292,"remaining_time":5.503977178},
{"learn":[7.719346395],"iteration":31,"passed_time":0.1766310178,"remaining_time":5.343088288},
{"learn":[7.624163594],"iteration":32,"passed_time":0.1772000417,"remaining_time":5.192498191},
{"learn":[7.524952543],"iteration":33,"passed_time":0.1777824606,"remaining_time":5.051113441},
{"learn":[7.424464745],"iteration":34,"passed_time":0.1784365361,"remaining_time":4.919750209},
{"learn":[7.327482321],"iteration":35,"passed_time":0.1791422936,"remaining_time":4.797032529},
{"learn":[7.238666841],"iteration":36,"passed_time":0.1797642117,"remaining_time":4.678727998},
{"learn":[7.158842395],"iteration":37,"passed_time":0.1804715378,"remaining_time":4.568779457},
{"learn":[7.074348246],"iteration":38,"passed_time":0.1810412642,"remaining_time":4.461042433},
{"learn":[6.992269093],"iteration":39,"passed_time":0.1817690431,"remaining_time":4.362457033},
{"learn":[6.925219745],"iteration":40,"passed_time":0.182417799,"remaining_time":4.266796811},
{"learn":[6.86013671],"iteration":41,"passed_time":0.1830332556,"remaining_time":4.174901403},
{"learn":[6.786739622],"iteration":42,"passed_time":0.1835937744,"remaining_time":4.086028886},
{"learn":[6.73057926],"iteration":43,"passed_time":0.184181072,"remaining_time":4.001752384},
{"learn":[6.666356486],"iteration":44,"passed_time":0.1849123204,"remaining_time":3.924250356},
{"learn":[6.606182832],"iteration":45,"passed_time":0.1855476734,"remaining_time":3.848097401},
{"learn":[6.547854615],"iteration":46,"passed_time":0.1861473835,"remaining_time":3.774435244},
{"learn":[6.49240675],"iteration":47,"passed_time":0.1867416239,"remaining_time":3.703708873},
{"learn":[6.431317261],"iteration":48,"passed_time":0.1874768351,"remaining_time":3.638581023},
{"learn":[6.377586395],"iteration":49,"passed_time":0.1881786568,"remaining_time":3.575394479},
{"learn":[6.327558015],"iteration":50,"passed_time":0.1889127858,"remaining_time":3.515259484},
{"learn":[6.282040317],"iteration":51,"passed_time":0.1895760576,"remaining_time":3.456117358},
{"learn":[6.237655841],"iteration":52,"passed_time":0.1901778399,"remaining_time":3.39808329},
{"learn":[6.192792003],"iteration":53,"passed_time":0.1907009817,"remaining_time":3.340798679},
{"learn":[6.150579347],"iteration":54,"passed_time":0.1913789312,"remaining_time":3.288238},
{"learn":[6.115693845],"iteration":55,"passed_time":0.1920088748,"remaining_time":3.236721033},
{"learn":[6.078780782],"iteration":56,"passed_time":0.1926045975,"remaining_time":3.186423429},
{"learn":[6.045146957],"iteration":57,"passed_time":0.1932091147,"remaining_time":3.137982517},
{"learn":[6.008080327],"iteration":58,"passed_time":0.1938180597,"remaining_time":3.091233799},
{"learn":[5.977575734],"iteration":59,"passed_time":0.194580347,"remaining_time":3.048425437},
{"learn":[5.948036502],"iteration":60,"passed_time":0.1952248169,"remaining_time":3.005182017},
{"learn":[5.914888282],"iteration":61,"passed_time":0.195868093,"remaining_time":2.963294698},
{"learn":[5.884957796],"iteration":62,"passed_time":0.1964939282,"remaining_time":2.922457313},
{"learn":[5.849539885],"iteration":63,"passed_time":0.1970797119,"remaining_time":2.882290787},
{"learn":[5.821387627],"iteration":64,"passed_time":0.197704276,"remaining_time":2.84389997},
{"learn":[5.797012279],"iteration":65,"passed_time":0.1983583117,"remaining_time":2.807070653},
{"learn":[5.768685095],"iteration":66,"passed_time":0.199000277,"remaining_time":2.771153111},
{"learn":[5.755484587],"iteration":67,"passed_time":0.1993771003,"remaining_time":2.73263908},
{"learn":[5.731887055],"iteration":68,"passed_time":0.1999941989,"remaining_time":2.698472452},
{"learn":[5.707148487],"iteration":69,"passed_time":0.200618351,"remaining_time":2.665358092},
{"learn":[5.685365039],"iteration":70,"passed_time":0.2013249701,"remaining_time":2.634237989},
{"learn":[5.663541834],"iteration":71,"passed_time":0.2019856373,"remaining_time":2.603370436},
{"learn":[5.638108797],"iteration":72,"passed_time":0.2025822403,"remaining_time":2.572516942},
{"learn":[5.619204893],"iteration":73,"passed_time":0.2031750366,"remaining_time":2.542433566},
{"learn":[5.598472793],"iteration":74,"passed_time":0.2037349758,"remaining_time":2.512731368},
{"learn":[5.577007075],"iteration":75,"passed_time":0.2044641253,"remaining_time":2.485853313},
{"learn":[5.562637084],"iteration":76,"passed_time":0.2051496422,"remaining_time":2.459131425},
{"learn":[5.54729991],"iteration":77,"passed_time":0.2058215285,"remaining_time":2.432916016},
{"learn":[5.530737623],"iteration":78,"passed_time":0.2063832894,"remaining_time":2.406063412},
{"learn":[5.513704873],"iteration":79,"passed_time":0.206962526,"remaining_time":2.38006905},
{"learn":[5.501575529],"iteration":80,"passed_time":0.2076765182,"remaining_time":2.356231114},
{"learn":[5.484080734],"iteration":81,"passed_time":0.2084389962,"remaining_time":2.333499982},
{"learn":[5.472178894],"iteration":82,"passed_time":0.209090195,"remaining_time":2.310068781},
{"learn":[5.458923342],"iteration":83,"passed_time":0.2097004123,"remaining_time":2.286733068},
{"learn":[5.451382371],"iteration":84,"passed_time":0.2101515373,"remaining_time":2.26221949},
{"learn":[5.441410748],"iteration":85,"passed_time":0.2108402861,"remaining_time":2.240790947},
{"learn":[5.434047468],"iteration":86,"passed_time":0.2113103321,"remaining_time":2.21754406},
{"learn":[5.422107497],"iteration":87,"passed_time":0.2119899531,"remaining_time":2.196986786},
{"learn":[5.40731265],"iteration":88,"passed_time":0.2125842505,"remaining_time":2.176002833},
{"learn":[5.396360181],"iteration":89,"passed_time":0.2131177511,"remaining_time":2.154857261},
{"learn":[5.383793239],"iteration":90,"passed_time":0.2137971616,"remaining_time":2.135622197},
{"learn":[5.369605034],"iteration":91,"passed_time":0.2143959986,"remaining_time":2.115995291},
{"learn":[5.357467333],"iteration":92,"passed_time":0.2149774602,"remaining_time":2.096608133},
{"learn":[5.341109968],"iteration":93,"passed_time":0.2156051686,"remaining_time":2.078066838},
{"learn":[5.330529276],"iteration":94,"passed_time":0.2162304883,"remaining_time":2.059879915},
{"learn":[5.319862075],"iteration":95,"passed_time":0.2168545703,"remaining_time":2.042047203},
{"learn":[5.313052243],"iteration":96,"passed_time":0.2174260473,"remaining_time":2.024079595},
{"learn":[5.299677207],"iteration":97,"passed_time":0.2179972348,"remaining_time":2.006464344},
{"learn":[5.287546698],"iteration":98,"passed_time":0.2186655167,"remaining_time":1.990077076},
{"learn":[5.279803754],"iteration":99,"passed_time":0.2192329599,"remaining_time":1.973096639},
{"learn":[5.272254612],"iteration":100,"passed_time":0.2197968984,"remaining_time":1.956410016},
{"learn":[5.268813888],"iteration":101,"passed_time":0.2201825449,"remaining_time":1.938469856},
{"learn":[5.258113767],"iteration":102,"passed_time":0.2208603384,"remaining_time":1.923414792},
{"learn":[5.251018576],"iteration":103,"passed_time":0.2214349012,"remaining_time":1.907746841},
{"learn":[5.24171237],"iteration":104,"passed_time":0.2219701504,"remaining_time":1.892031282},
{"learn":[5.233984943],"iteration":105,"passed_time":0.2226399842,"remaining_time":1.877737225},
{"learn":[5.226240449],"iteration":106,"passed_time":0.2234182367,"remaining_time":1.864602667},
{"learn":[5.220541644],"iteration":107,"passed_time":0.2240182273,"remaining_time":1.850224618},
{"learn":[5.211712096],"iteration":108,"passed_time":0.2246872791,"remaining_time":1.836663905},
{"learn":[5.203388597],"iteration":109,"passed_time":0.2252894708,"remaining_time":1.822796628},
{"learn":[5.196026544],"iteration":110,"passed_time":0.2259050489,"remaining_time":1.809275572},
{"learn":[5.188716772],"iteration":111,"passed_time":0.22651996,"remaining_time":1.795979683},
{"learn":[5.182163132],"iteration":112,"passed_time":0.2271917185,"remaining_time":1.783354463},
{"learn":[5.17764747],"iteration":113,"passed_time":0.2277905254,"remaining_time":1.770371978},
{"learn":[5.170548056],"iteration":114,"passed_time":0.2283076766,"remaining_time":1.756976468},
{"learn":[5.165901827],"iteration":115,"passed_time":0.2287514173,"remaining_time":1.743243559},
{"learn":[5.160333668],"iteration":116,"passed_time":0.2292987528,"remaining_time":1.730519647},
{"learn":[5.148953243],"iteration":117,"passed_time":0.2299566666,"remaining_time":1.718828644},
{"learn":[5.144729126],"iteration":118,"passed_time":0.2305049147,"remaining_time":1.706511175},
{"learn":[5.139939946],"iteration":119,"passed_time":0.2310518392,"remaining_time":1.694380154},
{"learn":[5.132898872],"iteration":120,"passed_time":0.2316905973,"remaining_time":1.683107728},
{"learn":[5.129073077],"iteration":121,"passed_time":0.2322800373,"remaining_time":1.671654695},
{"learn":[5.127123916],"iteration":122,"passed_time":0.232687242,"remaining_time":1.659078953},
{"learn":[5.121282057],"iteration":123,"passed_time":0.233259562,"remaining_time":1.647865938},
{"learn":[5.114489821],"iteration":124,"passed_time":0.2338488933,"remaining_time":1.636942253},
{"learn":[5.107777291],"iteration":125,"passed_time":0.2345220646,"remaining_time":1.626764162},
{"learn":[5.103518754],"iteration":126,"passed_time":0.2351235852,"remaining_time":1.616243227},
{"learn":[5.101133351],"iteration":127,"passed_time":0.2355171665,"remaining_time":1.604460697},
{"learn":[5.096462705],"iteration":128,"passed_time":0.2362801359,"remaining_time":1.595348825},
{"learn":[5.08562082],"iteration":129,"passed_time":0.2368940398,"remaining_time":1.585367805},
{"learn":[5.080483682],"iteration":130,"passed_time":0.2375162384,"remaining_time":1.575584818},
{"learn":[5.07437499],"iteration":131,"passed_time":0.2381489643,"remaining_time":1.566009856},
{"learn":[5.070683732],"iteration":132,"passed_time":0.2387552661,"remaining_time":1.556397111},
{"learn":[5.06432037],"iteration":133,"passed_time":0.2394100544,"remaining_time":1.547232142},
{"learn":[5.057436484],"iteration":134,"passed_time":0.2401043114,"remaining_time":1.538446143},
{"learn":[5.053254656],"iteration":135,"passed_time":0.2411215858,"remaining_time":1.531831251},
{"learn":[5.04801663],"iteration":136,"passed_time":0.2418198217,"remaining_time":1.523288366},
{"learn":[5.045680836],"iteration":137,"passed_time":0.2428126207,"remaining_time":1.516699124},
{"learn":[5.041857933],"iteration":138,"passed_time":0.2438231932,"remaining_time":1.510300499},
{"learn":[5.035264888],"iteration":139,"passed_time":0.2446820335,"remaining_time":1.503046777},
{"learn":[5.028771948],"iteration":140,"passed_time":0.2455141161,"remaining_time":1.49572075},
{"learn":[5.024912247],"iteration":141,"passed_time":0.2462527221,"remaining_time":1.487921377},
{"learn":[5.02239068],"iteration":142,"passed_time":0.2469362416,"remaining_time":1.479890622},
{"learn":[5.017110572],"iteration":143,"passed_time":0.2475907122,"remaining_time":1.471789234},
{"learn":[5.010707886],"iteration":144,"passed_time":0.2482883174,"remaining_time":1.464044906},
{"learn":[5.004389868],"iteration":145,"passed_time":0.2491039944,"remaining_time":1.457087748},
{"learn":[4.997628683],"iteration":146,"passed_time":0.2498734666,"remaining_time":1.449946034},
{"learn":[4.991497851],"iteration":147,"passed_time":0.2505408458,"remaining_time":1.442302707},
{"learn":[4.988345253],"iteration":148,"passed_time":0.2511076657,"remaining_time":1.434178682},
{"learn":[4.98460423],"iteration":149,"passed_time":0.2518226898,"remaining_time":1.426995242},
{"learn":[4.982441783],"iteration":150,"passed_time":0.2525366923,"remaining_time":1.419891734},
{"learn":[4.977461771],"iteration":151,"passed_time":0.2532443332,"remaining_time":1.412836806},
{"learn":[4.973601586],"iteration":152,"passed_time":0.2539407243,"remaining_time":1.405802572},
{"learn":[4.968328804],"iteration":153,"passed_time":0.254552114,"remaining_time":1.398383691},
{"learn":[4.9640736],"iteration":154,"passed_time":0.2552906587,"remaining_time":1.391745849},
{"learn":[4.960865882],"iteration":155,"passed_time":0.2560081484,"remaining_time":1.385069726},
{"learn":[4.957014156],"iteration":156,"passed_time":0.2567756359,"remaining_time":1.378737969},
{"learn":[4.952244852],"iteration":157,"passed_time":0.2573906702,"remaining_time":1.371664205},
{"learn":[4.949695675],"iteration":158,"passed_time":0.2579603553,"remaining_time":1.364431816},
{"learn":[4.946584698],"iteration":159,"passed_time":0.2585033027,"remaining_time":1.357142339},
{"learn":[4.940192834],"iteration":160,"passed_time":0.2593574647,"remaining_time":1.351558465},
{"learn":[4.936727994],"iteration":161,"passed_time":0.2600432166,"remaining_time":1.345161824},
{"learn":[4.932342063],"iteration":162,"passed_time":0.2607318135,"remaining_time":1.338849865},
{"learn":[4.925830838],"iteration":163,"passed_time":0.2616834482,"remaining_time":1.333947334},
{"learn":[4.922571773],"iteration":164,"passed_time":0.2624341844,"remaining_time":1.328076024},
{"learn":[4.918395814],"iteration":165,"passed_time":0.263088901,"remaining_time":1.321783996},
{"learn":[4.911142452],"iteration":166,"passed_time":0.2637101079,"remaining_time":1.315392334},
{"learn":[4.908276131],"iteration":167,"passed_time":0.2646006252,"remaining_time":1.310403096},
{"learn":[4.904584645],"iteration":168,"passed_time":0.2654650254,"remaining_time":1.305333941},
{"learn":[4.89795517],"iteration":169,"passed_time":0.2661094081,"remaining_time":1.299240051},
{"learn":[4.895556491],"iteration":170,"passed_time":0.2668286682,"remaining_time":1.2935729},
{"learn":[4.890591233],"iteration":171,"passed_time":0.2675094227,"remaining_time":1.287777918},
{"learn":[4.884629277],"iteration":172,"passed_time":0.2682950425,"remaining_time":1.282543353},
{"learn":[4.880550786],"iteration":173,"passed_time":0.2689035066,"remaining_time":1.276518945},
{"learn":[4.876384842],"iteration":174,"passed_time":0.2694808754,"remaining_time":1.270409841},
{"learn":[4.872638238],"iteration":175,"passed_time":0.270188876,"remaining_time":1.264975192},
{"learn":[4.869137118],"iteration":176,"passed_time":0.2708299137,"remaining_time":1.259282593},
{"learn":[4.863587157],"iteration":177,"passed_time":0.2716062114,"remaining_time":1.254271381},
{"learn":[4.858028614],"iteration":178,"passed_time":0.272307399,"remaining_time":1.248962986},
{"learn":[4.853838176],"iteration":179,"passed_time":0.2729430528,"remaining_time":1.243407241},
{"learn":[4.853462329],"iteration":180,"passed_time":0.2732686733,"remaining_time":1.236503002},
{"learn":[4.851573196],"iteration":181,"passed_time":0.2738954717,"remaining_time":1.231024702},
{"learn":[4.848442087],"iteration":182,"passed_time":0.2745531423,"remaining_time":1.225737253},
{"learn":[4.845547104],"iteration":183,"passed_time":0.2751268345,"remaining_time":1.220127701},
{"learn":[4.839868817],"iteration":184,"passed_time":0.2757689987,"remaining_time":1.214874238},
{"learn":[4.836336958],"iteration":185,"passed_time":0.276298783,"remaining_time":1.209178545},
{"learn":[4.831124789],"iteration":186,"passed_time":0.2768937285,"remaining_time":1.203821397},
{"learn":[4.827407333],"iteration":187,"passed_time":0.2775367944,"remaining_time":1.19872275},
{"learn":[4.824088918],"iteration":188,"passed_time":0.2780894491,"remaining_time":1.193283297},
{"learn":[4.820934539],"iteration":189,"passed_time":0.2787031025,"remaining_time":1.188155332},
{"learn":[4.816975227],"iteration":190,"passed_time":0.2792810323,"remaining_time":1.182923325},
{"learn":[4.812340486],"iteration":191,"passed_time":0.2798664699,"remaining_time":1.177771394},
{"learn":[4.806402747],"iteration":192,"passed_time":0.2804834748,"remaining_time":1.172798778},
{"learn":[4.801521788],"iteration":193,"passed_time":0.2812022449,"remaining_time":1.168293863},
{"learn":[4.797601172],"iteration":194,"passed_time":0.2818845707,"remaining_time":1.16367733},
{"learn":[4.792694629],"iteration":195,"passed_time":0.2825391825,"remaining_time":1.158987259},
{"learn":[4.789794613],"iteration":196,"passed_time":0.2831172437,"remaining_time":1.154026125},
{"learn":[4.785367055],"iteration":197,"passed_time":0.2837272722,"remaining_time":1.149238749},
{"learn":[4.780376856],"iteration":198,"passed_time":0.2845921845,"remaining_time":1.145519295},
{"learn":[4.776691261],"iteration":199,"passed_time":0.2852045559,"remaining_time":1.140818224},
{"learn":[4.773470753],"iteration":200,"passed_time":0.2860084386,"remaining_time":1.136919117},
{"learn":[4.77207327],"iteration":201,"passed_time":0.2866526364,"remaining_time":1.132419821},
{"learn":[4.767347177],"iteration":202,"passed_time":0.2872851434,"remaining_time":1.127912607},
{"learn":[4.763983068],"iteration":203,"passed_time":0.2879154666,"remaining_time":1.12343486},
{"learn":[4.761588849],"iteration":204,"passed_time":0.2885074514,"remaining_time":1.11884597},
{"learn":[4.758558086],"iteration":205,"passed_time":0.2891101668,"remaining_time":1.114337245},
{"learn":[4.753678804],"iteration":206,"passed_time":0.2896907628,"remaining_time":1.109781521},
{"learn":[4.746510889],"iteration":207,"passed_time":0.2903445462,"remaining_time":1.105542695},
{"learn":[4.744840601],"iteration":208,"passed_time":0.2913993199,"remaining_time":1.102855799},
{"learn":[4.741702222],"iteration":209,"passed_time":0.2921207745,"remaining_time":1.098930532},
{"learn":[4.739352853],"iteration":210,"passed_time":0.2927483727,"remaining_time":1.094684673},
{"learn":[4.735539287],"iteration":211,"passed_time":0.2933297687,"remaining_time":1.090301216},
{"learn":[4.730726751],"iteration":212,"passed_time":0.293978915,"remaining_time":1.086203785},
{"learn":[4.726416092],"iteration":213,"passed_time":0.2946201375,"remaining_time":1.082109477},
{"learn":[4.721293082],"iteration":214,"passed_time":0.2952157704,"remaining_time":1.077880836},
{"learn":[4.718443695],"iteration":215,"passed_time":0.2958523334,"remaining_time":1.073834395},
{"learn":[4.711627962],"iteration":216,"passed_time":0.296559154,"remaining_time":1.070072892},
{"learn":[4.709790764],"iteration":217,"passed_time":0.2971557983,"remaining_time":1.065944194},
{"learn":[4.706913073],"iteration":218,"passed_time":0.2977616664,"remaining_time":1.061880646},
{"learn":[4.703846389],"iteration":219,"passed_time":0.2983373937,"remaining_time":1.057741669},
{"learn":[4.701001135],"iteration":220,"passed_time":0.2988770568,"remaining_time":1.053507816},
{"learn":[4.700380864],"iteration":221,"passed_time":0.2993922259,"remaining_time":1.049221404},
{"learn":[4.695837486],"iteration":222,"passed_time":0.2999363971,"remaining_time":1.045069868},
{"learn":[4.691242996],"iteration":223,"passed_time":0.3004715005,"remaining_time":1.040919127},
{"learn":[4.690284609],"iteration":224,"passed_time":0.3010654188,"remaining_time":1.037003109},
{"learn":[4.68827119],"iteration":225,"passed_time":0.3016794116,"remaining_time":1.033185241},
{"learn":[4.686922425],"iteration":226,"passed_time":0.302319432,"remaining_time":1.029484233},
{"learn":[4.686085874],"iteration":227,"passed_time":0.3029045731,"remaining_time":1.025624256},
{"learn":[4.683230741],"iteration":228,"passed_time":0.3035162533,"remaining_time":1.021882233},
{"learn":[4.6773487],"iteration":229,"passed_time":0.3041421485,"remaining_time":1.018215019},
{"learn":[4.671462906],"iteration":230,"passed_time":0.3047472278,"remaining_time":1.014504841},
{"learn":[4.664799601],"iteration":231,"passed_time":0.305306304,"remaining_time":1.010669144},
{"learn":[4.660979386],"iteration":232,"passed_time":0.3058796556,"remaining_time":1.006908566},
{"learn":[4.656281279],"iteration":233,"passed_time":0.3064535682,"remaining_time":1.003177065},
{"learn":[4.651997094],"iteration":234,"passed_time":0.3070953836,"remaining_time":0.9996934828},
{"learn":[4.650151977],"iteration":235,"passed_time":0.3076912162,"remaining_time":0.9960851236},
{"learn":[4.648478046],"iteration":236,"passed_time":0.3082831108,"remaining_time":0.9924895087},
{"learn":[4.646364602],"iteration":237,"passed_time":0.3088211149,"remaining_time":0.9887465948},
{"learn":[4.642635873],"iteration":238,"passed_time":0.3094211695,"remaining_time":0.9852280754},
{"learn":[4.640860821],"iteration":239,"passed_time":0.3099852747,"remaining_time":0.9816200364},
{"learn":[4.639446822],"iteration":240,"passed_time":0.3106243947,"remaining_time":0.9782735085},
{"learn":[4.637120072],"iteration":241,"passed_time":0.3112298052,"remaining_time":0.97484377},
{"learn":[4.633769267],"iteration":242,"passed_time":0.3118646764,"remaining_time":0.9715290537},
{"learn":[4.630491517],"iteration":243,"passed_time":0.312470556,"remaining_time":0.9681464768},
{"learn":[4.627813333],"iteration":244,"passed_time":0.3130993664,"remaining_time":0.9648572312},
{"learn":[4.622496304],"iteration":245,"passed_time":0.3137617278,"remaining_time":0.9616924503},
{"learn":[4.618979301],"iteration":246,"passed_time":0.3143697512,"remaining_time":0.958382278},
{"learn":[4.616563458],"iteration":247,"passed_time":0.3149410091,"remaining_time":0.9549824146},
{"learn":[4.614759385],"iteration":248,"passed_time":0.3156623043,"remaining_time":0.9520577932},
{"learn":[4.61251363],"iteration":249,"passed_time":0.3162559933,"remaining_time":0.94876798},
{"learn":[4.608796693],"iteration":250,"passed_time":0.3170337203,"remaining_time":0.9460488307},
{"learn":[4.60847774],"iteration":251,"passed_time":0.3175973859,"remaining_time":0.9427097009},
{"learn":[4.605195659],"iteration":252,"passed_time":0.3181538659,"remaining_time":0.9393712957},
{"learn":[4.60103766],"iteration":253,"passed_time":0.3187226906,"remaining_time":0.936091052},
{"learn":[4.599325598],"iteration":254,"passed_time":0.3193045289,"remaining_time":0.9328700942},
{"learn":[4.597012808],"iteration":255,"passed_time":0.3199782511,"remaining_time":0.9299367924},
{"learn":[4.594161533],"iteration":256,"passed_time":0.320583149,"remaining_time":0.9268220999},
{"learn":[4.592197259],"iteration":257,"passed_time":0.3211490576,"remaining_time":0.9236147315},
{"learn":[4.58952828],"iteration":258,"passed_time":0.3217464842,"remaining_time":0.9205179336},
{"learn":[4.585816572],"iteration":259,"passed_time":0.3223068727,"remaining_time":0.9173349454},
{"learn":[4.582934052],"iteration":260,"passed_time":0.3229116224,"remaining_time":0.9142976588},
{"learn":[4.582234842],"iteration":261,"passed_time":0.323581798,"remaining_time":0.9114632326},
{"learn":[4.57571562],"iteration":262,"passed_time":0.3241461035,"remaining_time":0.9083485867},
{"learn":[4.571197349],"iteration":263,"passed_time":0.324798856,"remaining_time":0.9054998409},
{"learn":[4.56723703],"iteration":264,"passed_time":0.3253815042,"remaining_time":0.9024732285},
{"learn":[4.560335567],"iteration":265,"passed_time":0.3260648235,"remaining_time":0.8997427837},
{"learn":[4.554709345],"iteration":266,"passed_time":0.3269525768,"remaining_time":0.8975889095},
{"learn":[4.552806306],"iteration":267,"passed_time":0.327505183,"remaining_time":0.8945290819},
{"learn":[4.550766241],"iteration":268,"passed_time":0.3282288427,"remaining_time":0.8919527287},
{"learn":[4.549216045],"iteration":269,"passed_time":0.3288376275,"remaining_time":0.8890795113},
{"learn":[4.547687452],"iteration":270,"passed_time":0.3294677903,"remaining_time":0.8862805134},
{"learn":[4.545642435],"iteration":271,"passed_time":0.3301365832,"remaining_time":0.8836008549},
{"learn":[4.543930359],"iteration":272,"passed_time":0.3307130804,"remaining_time":0.8806901444},
{"learn":[4.541029943],"iteration":273,"passed_time":0.3313419309,"remaining_time":0.8779351891},
{"learn":[4.537781449],"iteration":274,"passed_time":0.3319508844,"remaining_time":0.8751432406},
{"learn":[4.53066128],"iteration":275,"passed_time":0.3325581579,"remaining_time":0.8723627042},
{"learn":[4.526763956],"iteration":276,"passed_time":0.3332016746,"remaining_time":0.8696924574},
{"learn":[4.522036004],"iteration":277,"passed_time":0.3338566337,"remaining_time":0.8670665091},
{"learn":[4.515307629],"iteration":278,"passed_time":0.3344884507,"remaining_time":0.8643948851},
{"learn":[4.51109143],"iteration":279,"passed_time":0.335084633,"remaining_time":0.8616461991},
{"learn":[4.508233494],"iteration":280,"passed_time":0.3357388799,"remaining_time":0.8590614045},
{"learn":[4.502555629],"iteration":281,"passed_time":0.3363534061,"remaining_time":0.8563891687},
{"learn":[4.500081355],"iteration":282,"passed_time":0.3368891106,"remaining_time":0.853531775},
{"learn":[4.495281743],"iteration":283,"passed_time":0.3376215156,"remaining_time":0.851186638},
{"learn":[4.492138869],"iteration":284,"passed_time":0.3382162954,"remaining_time":0.8485075482},
{"learn":[4.491708261],"iteration":285,"passed_time":0.3387186706,"remaining_time":0.8456123454},
{"learn":[4.489398865],"iteration":286,"passed_time":0.3393545748,"remaining_time":0.8430655465},
{"learn":[4.485796373],"iteration":287,"passed_time":0.3403646846,"remaining_time":0.841457137},
{"learn":[4.479542205],"iteration":288,"passed_time":0.3410247517,"remaining_time":0.8389916901},
{"learn":[4.475986993],"iteration":289,"passed_time":0.341609595,"remaining_time":0.8363545256},
{"learn":[4.468661855],"iteration":290,"passed_time":0.3422213866,"remaining_time":0.833797124},
{"learn":[4.463785664],"iteration":291,"passed_time":0.3428315237,"remaining_time":0.831249037},
{"learn":[4.460445831],"iteration":292,"passed_time":0.3433871537,"remaining_time":0.8285826543},
{"learn":[4.45692492],"iteration":293,"passed_time":0.3439939762,"remaining_time":0.8260535619},
{"learn":[4.454031688],"iteration":294,"passed_time":0.3447005063,"remaining_time":0.8237757863},
{"learn":[4.451672391],"iteration":295,"passed_time":0.3453230155,"remaining_time":0.8213087936},
{"learn":[4.45031553],"iteration":296,"passed_time":0.3459275241,"remaining_time":0.8188116144},
{"learn":[4.446782666],"iteration":297,"passed_time":0.3465656126,"remaining_time":0.8164062418},
{"learn":[4.444369689],"iteration":298,"passed_time":0.347119892,"remaining_time":0.8138162017},
{"learn":[4.44411683],"iteration":299,"passed_time":0.3476977617,"remaining_time":0.8112947773},
{"learn":[4.440876943],"iteration":300,"passed_time":0.3482987741,"remaining_time":0.8088400103},
{"learn":[4.439336453],"iteration":301,"passed_time":0.3489953252,"remaining_time":0.8066183345},
{"learn":[4.436666901],"iteration":302,"passed_time":0.349635845,"remaining_time":0.8042778348},
{"learn":[4.433043336],"iteration":303,"passed_time":0.3502250348,"remaining_time":0.8018310008},
{"learn":[4.431419305],"iteration":304,"passed_time":0.3508980844,"remaining_time":0.7995874381},
{"learn":[4.428859646],"iteration":305,"passed_time":0.3515431018,"remaining_time":0.7972905643},
{"learn":[4.424552441],"iteration":306,"passed_time":0.3521423396,"remaining_time":0.7949011118},
{"learn":[4.422706391],"iteration":307,"passed_time":0.3528172105,"remaining_time":0.7926932133},
{"learn":[4.421427994],"iteration":308,"passed_time":0.3533871861,"remaining_time":0.7902606654},
{"learn":[4.418733158],"iteration":309,"passed_time":0.354055228,"remaining_time":0.7880584106},
{"learn":[4.415656941],"iteration":310,"passed_time":0.3547133524,"remaining_time":0.7858440509},
{"learn":[4.410747417],"iteration":311,"passed_time":0.3553738809,"remaining_time":0.7836449681},
{"learn":[4.408126521],"iteration":312,"passed_time":0.3560336765,"remaining_time":0.7814541079},
{"learn":[4.407843853],"iteration":313,"passed_time":0.3566973202,"remaining_time":0.7792814066},
{"learn":[4.405219398],"iteration":314,"passed_time":0.357362255,"remaining_time":0.7771210942},
{"learn":[4.402708465],"iteration":315,"passed_time":0.3579915077,"remaining_time":0.7748930104},
{"learn":[4.40104971],"iteration":316,"passed_time":0.3585851054,"remaining_time":0.7725981924},
{"learn":[4.400830038],"iteration":317,"passed_time":0.3592815864,"remaining_time":0.770534723},
{"learn":[4.39784288],"iteration":318,"passed_time":0.3598466044,"remaining_time":0.7681991773},
{"learn":[4.393741845],"iteration":319,"passed_time":0.3604468551,"remaining_time":0.7659495671},
{"learn":[4.393425936],"iteration":320,"passed_time":0.3610177335,"remaining_time":0.763648103},
{"learn":[4.390505974],"iteration":321,"passed_time":0.3616287835,"remaining_time":0.7614419727},
{"learn":[4.390305136],"iteration":322,"passed_time":0.3622228019,"remaining_time":0.7592100214},
{"learn":[4.38568203],"iteration":323,"passed_time":0.3628460524,"remaining_time":0.7570491711},
{"learn":[4.383057135],"iteration":324,"passed_time":0.3634510519,"remaining_time":0.7548598771},
{"learn":[4.380662684],"iteration":325,"passed_time":0.3641113239,"remaining_time":0.7527945776},
{"learn":[4.37805727],"iteration":326,"passed_time":0.3647092984,"remaining_time":0.7506096571},
{"learn":[4.373708319],"iteration":327,"passed_time":0.3652920468,"remaining_time":0.7484032178},
{"learn":[4.36887921],"iteration":328,"passed_time":0.3659428862,"remaining_time":0.7463455216},
{"learn":[4.367895929],"iteration":329,"passed_time":0.3665695619,"remaining_time":0.7442472923},
{"learn":[4.362140573],"iteration":330,"passed_time":0.3672613745,"remaining_time":0.742289606},
{"learn":[4.361931924],"iteration":331,"passed_time":0.3680863345,"remaining_time":0.7406074441},
{"learn":[4.359656377],"iteration":332,"passed_time":0.3687209106,"remaining_time":0.7385490912},
{"learn":[4.354281355],"iteration":333,"passed_time":0.3694020637,"remaining_time":0.736592139},
{"learn":[4.348589447],"iteration":334,"passed_time":0.3700171912,"remaining_time":0.7345117379},
{"learn":[4.346355698],"iteration":335,"passed_time":0.3706248039,"remaining_time":0.7324252077},
{"learn":[4.343894047],"iteration":336,"passed_time":0.3711972439,"remaining_time":0.7302782572},
{"learn":[4.341561356],"iteration":337,"passed_time":0.3718429256,"remaining_time":0.7282840732},
{"learn":[4.338869061],"iteration":338,"passed_time":0.3725669156,"remaining_time":0.7264505345},
{"learn":[4.333720063],"iteration":339,"passed_time":0.3731480495,"remaining_time":0.7243462138},
{"learn":[4.330892223],"iteration":340,"passed_time":0.3737725669,"remaining_time":0.7223346673},
{"learn":[4.328311474],"iteration":341,"passed_time":0.3743412802,"remaining_time":0.7202238666},
{"learn":[4.324580133],"iteration":342,"passed_time":0.3749824217,"remaining_time":0.7182607902},
{"learn":[4.323354432],"iteration":343,"passed_time":0.3756043152,"remaining_time":0.7162686941},
{"learn":[4.323159553],"iteration":344,"passed_time":0.3762162277,"remaining_time":0.7142655916},
{"learn":[4.318639682],"iteration":345,"passed_time":0.3768459281,"remaining_time":0.7123041532},
{"learn":[4.312712208],"iteration":346,"passed_time":0.3774109749,"remaining_time":0.7102287223},
{"learn":[4.311461062],"iteration":347,"passed_time":0.3780897143,"remaining_time":0.708374982},
{"learn":[4.311178356],"iteration":348,"passed_time":0.3788063813,"remaining_time":0.7065987227},
{"learn":[4.311102505],"iteration":349,"passed_time":0.379407333,"remaining_time":0.7046136184},
{"learn":[4.310232308],"iteration":350,"passed_time":0.3800093056,"remaining_time":0.7026382887},
{"learn":[4.305128197],"iteration":351,"passed_time":0.3806158299,"remaining_time":0.7006791415},
{"learn":[4.304595496],"iteration":352,"passed_time":0.3811863556,"remaining_time":0.6986616772},
{"learn":[4.3004992],"iteration":353,"passed_time":0.3820150221,"remaining_time":0.6971234584},
{"learn":[4.297581524],"iteration":354,"passed_time":0.3826082,"remaining_time":0.6951613774},
{"learn":[4.297355825],"iteration":355,"passed_time":0.3831522348,"remaining_time":0.6931180876},
{"learn":[4.295758715],"iteration":356,"passed_time":0.3837387316,"remaining_time":0.6911596763},
{"learn":[4.292500657],"iteration":357,"passed_time":0.3844495381,"remaining_time":0.6894318533},
{"learn":[4.290797586],"iteration":358,"passed_time":0.3850811536,"remaining_time":0.6875682992},
{"learn":[4.286410608],"iteration":359,"passed_time":0.3857326541,"remaining_time":0.6857469406},
{"learn":[4.280278245],"iteration":360,"passed_time":0.3863691081,"remaining_time":0.6839054296},
{"learn":[4.279941283],"iteration":361,"passed_time":0.3869482701,"remaining_time":0.6819696031},
{"learn":[4.274426275],"iteration":362,"passed_time":0.3875178872,"remaining_time":0.6800245017},
{"learn":[4.273567658],"iteration":363,"passed_time":0.3881813897,"remaining_time":0.6782509996},
{"learn":[4.269488271],"iteration":364,"passed_time":0.3888973673,"remaining_time":0.6765748718},
{"learn":[4.266838205],"iteration":365,"passed_time":0.3894815897,"remaining_time":0.6746757593},
{"learn":[4.263456509],"iteration":366,"passed_time":0.390119157,"remaining_time":0.6728758212},
{"learn":[4.260360204],"iteration":367,"passed_time":0.3906998028,"remaining_time":0.6709844439},
{"learn":[4.255120549],"iteration":368,"passed_time":0.3913005532,"remaining_time":0.6691345503},
{"learn":[4.252582211],"iteration":369,"passed_time":0.391966049,"remaining_time":0.667401651},
{"learn":[4.247857931],"iteration":370,"passed_time":0.3925928571,"remaining_time":0.665608914},
{"learn":[4.245288911],"iteration":371,"passed_time":0.3932310855,"remaining_time":0.6638417249},
{"learn":[4.24048515],"iteration":372,"passed_time":0.3938815757,"remaining_time":0.662101201},
{"learn":[4.2378365],"iteration":373,"passed_time":0.3946050309,"remaining_time":0.6604886345},
{"learn":[4.236751063],"iteration":374,"passed_time":0.395293442,"remaining_time":0.6588224034},
{"learn":[4.233240093],"iteration":375,"passed_time":0.3960716441,"remaining_time":0.657310388},
{"learn":[4.230358421],"iteration":376,"passed_time":0.3966997842,"remaining_time":0.6555542853},
{"learn":[4.225853583],"iteration":377,"passed_time":0.3972733398,"remaining_time":0.6537143317},
{"learn":[4.224702126],"iteration":378,"passed_time":0.3979066036,"remaining_time":0.6519788941},
{"learn":[4.224361982],"iteration":379,"passed_time":0.3986333285,"remaining_time":0.6504017465},
{"learn":[4.223787954],"iteration":380,"passed_time":0.3992005207,"remaining_time":0.6485698748},
{"learn":[4.22144054],"iteration":381,"passed_time":0.399825065,"remaining_time":0.6468374088},
{"learn":[4.217739335],"iteration":382,"passed_time":0.4005660441,"remaining_time":0.6452983007},
{"learn":[4.215611665],"iteration":383,"passed_time":0.4011830647,"remaining_time":0.6435644996},
{"learn":[4.210236863],"iteration":384,"passed_time":0.4018408325,"remaining_time":0.6419015895},
{"learn":[4.208454294],"iteration":385,"passed_time":0.4024850212,"remaining_time":0.6402222876},
{"learn":[4.207446501],"iteration":386,"passed_time":0.4031053167,"remaining_time":0.6385104888},
{"learn":[4.204985442],"iteration":387,"passed_time":0.4036571697,"remaining_time":0.6366963605},
{"learn":[4.202796622],"iteration":388,"passed_time":0.4042774449,"remaining_time":0.6349961924},
{"learn":[4.199774004],"iteration":389,"passed_time":0.4049702494,"remaining_time":0.6334150054},
{"learn":[4.199458358],"iteration":390,"passed_time":0.4055527527,"remaining_time":0.6316665637},
{"learn":[4.19751254],"iteration":391,"passed_time":0.4061792706,"remaining_time":0.6299923381},
{"learn":[4.195201346],"iteration":392,"passed_time":0.4068144023,"remaining_time":0.6283367486},
{"learn":[4.190593508],"iteration":393,"passed_time":0.4074656427,"remaining_time":0.6267111154},
{"learn":[4.187212054],"iteration":394,"passed_time":0.4080804782,"remaining_time":0.6250346565},
{"learn":[4.184984466],"iteration":395,"passed_time":0.4088014328,"remaining_time":0.6235254177},
{"learn":[4.182832144],"iteration":396,"passed_time":0.4096607843,"remaining_time":0.62223036},
{"learn":[4.179752812],"iteration":397,"passed_time":0.4102798173,"remaining_time":0.620573995},
{"learn":[4.17878934],"iteration":398,"passed_time":0.4108360885,"remaining_time":0.6188282936},
{"learn":[4.174548229],"iteration":399,"passed_time":0.4114544506,"remaining_time":0.6171816758},
{"learn":[4.168872556],"iteration":400,"passed_time":0.4121003026,"remaining_time":0.61558125},
{"learn":[4.163926494],"iteration":401,"passed_time":0.412715187,"remaining_time":0.613939507},
{"learn":[4.159485076],"iteration":402,"passed_time":0.413333118,"remaining_time":0.6123073733},
{"learn":[4.155926102],"iteration":403,"passed_time":0.4139342807,"remaining_time":0.610655523},
{"learn":[4.153540115],"iteration":404,"passed_time":0.414495021,"remaining_time":0.6089494753},
{"learn":[4.150983044],"iteration":405,"passed_time":0.4152559769,"remaining_time":0.6075419957},
{"learn":[4.146539132],"iteration":406,"passed_time":0.4159386445,"remaining_time":0.606023627},
{"learn":[4.144869174],"iteration":407,"passed_time":0.41656964,"remaining_time":0.6044343796},
{"learn":[4.142825962],"iteration":408,"passed_time":0.41717101,"remaining_time":0.6028070096},
{"learn":[4.142467378],"iteration":409,"passed_time":0.4177943507,"remaining_time":0.6012162607},
{"learn":[4.141800768],"iteration":410,"passed_time":0.4184378989,"remaining_time":0.5996591787},
{"learn":[4.140107084],"iteration":411,"passed_time":0.4190584057,"remaining_time":0.598073647},
{"learn":[4.136243196],"iteration":412,"passed_time":0.4197261455,"remaining_time":0.5965599211},
{"learn":[4.133618439],"iteration":413,"passed_time":0.4203477543,"remaining_time":0.5949849856},
{"learn":[4.131053025],"iteration":414,"passed_time":0.4210093331,"remaining_time":0.5934709876},
{"learn":[4.128379975],"iteration":415,"passed_time":0.4216397464,"remaining_time":0.5919173363},
{"learn":[4.127068571],"iteration":416,"passed_time":0.4222258996,"remaining_time":0.5903062337},
{"learn":[4.125969877],"iteration":417,"passed_time":0.4228724316,"remaining_time":0.5887841033},
{"learn":[4.123893633],"iteration":418,"passed_time":0.423429686,"remaining_time":0.587142357},
{"learn":[4.119643722],"iteration":419,"passed_time":0.4240425095,"remaining_time":0.5855825131},
{"learn":[4.11465686],"iteration":420,"passed_time":0.4247021263,"remaining_time":0.5840915229},
{"learn":[4.111565986],"iteration":421,"passed_time":0.4252977795,"remaining_time":0.5825168638},
{"learn":[4.106322452],"iteration":422,"passed_time":0.4259238562,"remaining_time":0.5809883334},
{"learn":[4.104222175],"iteration":423,"passed_time":0.4265392026,"remaining_time":0.5794494828},
{"learn":[4.103008002],"iteration":424,"passed_time":0.4271382613,"remaining_time":0.5778929417},
{"learn":[4.099176337],"iteration":425,"passed_time":0.4277807017,"remaining_time":0.5763993493},
{"learn":[4.096525716],"iteration":426,"passed_time":0.4285122361,"remaining_time":0.5750293004},
{"learn":[4.094967724],"iteration":427,"passed_time":0.429141092,"remaining_time":0.5735250109},
{"learn":[4.094683584],"iteration":428,"passed_time":0.4297203041,"remaining_time":0.5719587264},
{"learn":[4.091096563],"iteration":429,"passed_time":0.4302875239,"remaining_time":0.5703811363},
{"learn":[4.089178677],"iteration":430,"passed_time":0.4309137105,"remaining_time":0.5688860819},
{"learn":[4.085335077],"iteration":431,"passed_time":0.4315376708,"remaining_time":0.5673921227},
{"learn":[4.084852122],"iteration":432,"passed_time":0.4321543195,"remaining_time":0.5658926078},
{"learn":[4.080322952],"iteration":433,"passed_time":0.4327976871,"remaining_time":0.5644320067},
{"learn":[4.077449519],"iteration":434,"passed_time":0.4334173412,"remaining_time":0.5629443627},
{"learn":[4.076568374],"iteration":435,"passed_time":0.4340413045,"remaining_time":0.5614662746},
{"learn":[4.076071793],"iteration":436,"passed_time":0.4346612692,"remaining_time":0.559986944},
{"learn":[4.075027644],"iteration":437,"passed_time":0.4353047472,"remaining_time":0.5585417076},
{"learn":[4.07020837],"iteration":438,"passed_time":0.435968234,"remaining_time":0.5571256931},
{"learn":[4.06833694],"iteration":439,"passed_time":0.4366288265,"remaining_time":0.5557094155},
{"learn":[4.063936568],"iteration":440,"passed_time":0.4372801983,"remaining_time":0.5542848772},
{"learn":[4.061734926],"iteration":441,"passed_time":0.4379147392,"remaining_time":0.5528425894},
{"learn":[4.060815619],"iteration":442,"passed_time":0.4384976278,"remaining_time":0.5513390039},
{"learn":[4.056407489],"iteration":443,"passed_time":0.4390784282,"remaining_time":0.5498369506},
{"learn":[4.05238936],"iteration":444,"passed_time":0.4397569126,"remaining_time":0.5484608685},
{"learn":[4.049685254],"iteration":445,"passed_time":0.4404184224,"remaining_time":0.5470668297},
{"learn":[4.045162016],"iteration":446,"passed_time":0.4411645923,"remaining_time":0.5457808043},
{"learn":[4.042955482],"iteration":447,"passed_time":0.4418053655,"remaining_time":0.5443673254},
{"learn":[4.041467663],"iteration":448,"passed_time":0.4424004103,"remaining_time":0.5429011717},
{"learn":[4.038920476],"iteration":449,"passed_time":0.4429251954,"remaining_time":0.5413530166},
{"learn":[4.036694383],"iteration":450,"passed_time":0.4435345512,"remaining_time":0.5399123472},
{"learn":[4.034999007],"iteration":451,"passed_time":0.44413935,"remaining_time":0.5384698314},
{"learn":[4.031928018],"iteration":452,"passed_time":0.4447006,"remaining_time":0.5369784288},
{"learn":[4.028718143],"iteration":453,"passed_time":0.4452963771,"remaining_time":0.5355326473},
{"learn":[4.027401978],"iteration":454,"passed_time":0.4459004188,"remaining_time":0.5341005016},
{"learn":[4.025930598],"iteration":455,"passed_time":0.4465160967,"remaining_time":0.5326858698},
{"learn":[4.021074523],"iteration":456,"passed_time":0.4470643145,"remaining_time":0.5311945793},
{"learn":[4.020268486],"iteration":457,"passed_time":0.4478235919,"remaining_time":0.5299571764},
{"learn":[4.017986361],"iteration":458,"passed_time":0.4484123594,"remaining_time":0.5285208855},
{"learn":[4.014814804],"iteration":459,"passed_time":0.4490275975,"remaining_time":0.5271193536},
{"learn":[4.009704796],"iteration":460,"passed_time":0.449622217,"remaining_time":0.5256971257},
{"learn":[4.008440457],"iteration":461,"passed_time":0.4502147428,"remaining_time":0.5242760424},
{"learn":[4.004854849],"iteration":462,"passed_time":0.4508723248,"remaining_time":0.5229339922},
{"learn":[4.000898028],"iteration":463,"passed_time":0.4514922093,"remaining_time":0.5215513452},
{"learn":[3.996617985],"iteration":464,"passed_time":0.4521207793,"remaining_time":0.5201819718},
{"learn":[3.995443319],"iteration":465,"passed_time":0.452791885,"remaining_time":0.5188645206},
{"learn":[3.990771995],"iteration":466,"passed_time":0.4534300937,"remaining_time":0.5175122911},
{"learn":[3.989249359],"iteration":467,"passed_time":0.4541743699,"remaining_time":0.5162836854},
{"learn":[3.986599538],"iteration":468,"passed_time":0.4548072776,"remaining_time":0.5149310542},
{"learn":[3.985628919],"iteration":469,"passed_time":0.4554097824,"remaining_time":0.5135472014},
{"learn":[3.985086112],"iteration":470,"passed_time":0.4559752611,"remaining_time":0.512125081},
{"learn":[3.98466839],"iteration":471,"passed_time":0.4566683874,"remaining_time":0.5108493825},
{"learn":[3.984233894],"iteration":472,"passed_time":0.4573058417,"remaining_time":0.5095141196},
{"learn":[3.981855845],"iteration":473,"passed_time":0.4579248367,"remaining_time":0.5081613167},
{"learn":[3.978684264],"iteration":474,"passed_time":0.4585597602,"remaining_time":0.5068292086},
{"learn":[3.974361269],"iteration":475,"passed_time":0.4591109423,"remaining_time":0.505407844},
{"learn":[3.972074049],"iteration":476,"passed_time":0.4596215621,"remaining_time":0.503945654},
{"learn":[3.97191982],"iteration":477,"passed_time":0.4601667147,"remaining_time":0.502525157},
{"learn":[3.969616848],"iteration":478,"passed_time":0.4607986406,"remaining_time":0.5012026968},
{"learn":[3.968533527],"iteration":479,"passed_time":0.4613980903,"remaining_time":0.4998479311},
{"learn":[3.967568753],"iteration":480,"passed_time":0.461951608,"remaining_time":0.4984467455},
{"learn":[3.966232553],"iteration":481,"passed_time":0.4624818829,"remaining_time":0.4970240982},
{"learn":[3.961522393],"iteration":482,"passed_time":0.463053029,"remaining_time":0.4956488944},
{"learn":[3.955829553],"iteration":483,"passed_time":0.4636927708,"remaining_time":0.494350144},
{"learn":[3.954248095],"iteration":484,"passed_time":0.4644036331,"remaining_time":0.4931296311},
{"learn":[3.951922606],"iteration":485,"passed_time":0.4651132066,"remaining_time":0.4919098522},
{"learn":[3.94978202],"iteration":486,"passed_time":0.4657475669,"remaining_time":0.49061294},
{"learn":[3.949518999],"iteration":487,"passed_time":0.4663777943,"remaining_time":0.4893144072},
{"learn":[3.945431216],"iteration":488,"passed_time":0.4669581679,"remaining_time":0.4879665108},
{"learn":[3.943249086],"iteration":489,"passed_time":0.4675586879,"remaining_time":0.4866427159},
{"learn":[3.941981548],"iteration":490,"passed_time":0.468221651,"remaining_time":0.4853865995},
{"learn":[3.936600517],"iteration":491,"passed_time":0.4688506217,"remaining_time":0.4840977964},
{"learn":[3.934476885],"iteration":492,"passed_time":0.4694564727,"remaining_time":0.4827878938},
{"learn":[3.93045798],"iteration":493,"passed_time":0.4700977569,"remaining_time":0.4815171356},
{"learn":[3.925977375],"iteration":494,"passed_time":0.4707378574,"remaining_time":0.4802477131},
{"learn":[3.92457993],"iteration":495,"passed_time":0.4712963279,"remaining_time":0.4788978816},
{"learn":[3.919849146],"iteration":496,"passed_time":0.4718952566,"remaining_time":0.4775921812},
{"learn":[3.919681964],"iteration":497,"passed_time":0.4726065832,"remaining_time":0.47640262},
{"learn":[3.917633027],"iteration":498,"passed_time":0.4732375586,"remaining_time":0.4751343024},
{"learn":[3.916616419],"iteration":499,"passed_time":0.4738422761,"remaining_time":0.4738422761},
{"learn":[3.912896166],"iteration":500,"passed_time":0.4746564878,"remaining_time":0.4727616515},
{"learn":[3.912769674],"iteration":501,"passed_time":0.4752379053,"remaining_time":0.4714511491},
{"learn":[3.909373788],"iteration":502,"passed_time":0.4758072288,"remaining_time":0.4701315959},
{"learn":[3.906706036],"iteration":503,"passed_time":0.476471752,"remaining_time":0.4689087083},
{"learn":[3.903895664],"iteration":504,"passed_time":0.4772273,"remaining_time":0.4677772545},
{"learn":[3.902982967],"iteration":505,"passed_time":0.4778202982,"remaining_time":0.4664885915},
{"learn":[3.900905528],"iteration":506,"passed_time":0.4784216797,"remaining_time":0.4652108246},
{"learn":[3.897463465],"iteration":507,"passed_time":0.4790057519,"remaining_time":0.4639189566},
{"learn":[3.895918033],"iteration":508,"passed_time":0.4796065628,"remaining_time":0.4626460163},
{"learn":[3.893921936],"iteration":509,"passed_time":0.4802934278,"remaining_time":0.4614583914},
{"learn":[3.890237934],"iteration":510,"passed_time":0.4809168486,"remaining_time":0.4602120137},
{"learn":[3.887311613],"iteration":511,"passed_time":0.4814769566,"remaining_time":0.4589077243},
{"learn":[3.884869735],"iteration":512,"passed_time":0.4821116876,"remaining_time":0.4576771771},
{"learn":[3.882101231],"iteration":513,"passed_time":0.4827146435,"remaining_time":0.4564189042},
{"learn":[3.88060368],"iteration":514,"passed_time":0.4837259809,"remaining_time":0.4555477685},
{"learn":[3.877726076],"iteration":515,"passed_time":0.4843124775,"remaining_time":0.4542775952},
{"learn":[3.874938145],"iteration":516,"passed_time":0.4849305485,"remaining_time":0.4530395646},
{"learn":[3.874340833],"iteration":517,"passed_time":0.485522353,"remaining_time":0.4517794867},
{"learn":[3.873105224],"iteration":518,"passed_time":0.4861592189,"remaining_time":0.4505637463},
{"learn":[3.869800236],"iteration":519,"passed_time":0.4867496294,"remaining_time":0.4493073502},
{"learn":[3.867932518],"iteration":520,"passed_time":0.4873108093,"remaining_time":0.4480266366},
{"learn":[3.866666962],"iteration":521,"passed_time":0.4878708172,"remaining_time":0.4467476065},
{"learn":[3.865527652],"iteration":522,"passed_time":0.4884748021,"remaining_time":0.4455114352},
{"learn":[3.861900081],"iteration":523,"passed_time":0.4891228872,"remaining_time":0.4443177372},
{"learn":[3.858502887],"iteration":524,"passed_time":0.489768898,"remaining_time":0.443124241},
{"learn":[3.858335097],"iteration":525,"passed_time":0.4903631067,"remaining_time":0.4418861456},
{"learn":[3.855719306],"iteration":526,"passed_time":0.4909356281,"remaining_time":0.4406310286},
{"learn":[3.855137428],"iteration":527,"passed_time":0.4914622364,"remaining_time":0.4393374537},
{"learn":[3.851985706],"iteration":528,"passed_time":0.4920405565,"remaining_time":0.4380928207},
{"learn":[3.851051809],"iteration":529,"passed_time":0.4926000149,"remaining_time":0.4368339755},
{"learn":[3.850679146],"iteration":530,"passed_time":0.4933755871,"remaining_time":0.4357686447},
{"learn":[3.848179484],"iteration":531,"passed_time":0.4939448903,"remaining_time":0.4345229486},
{"learn":[3.844551071],"iteration":532,"passed_time":0.4945636528,"remaining_time":0.4333231254},
{"learn":[3.841604794],"iteration":533,"passed_time":0.4951481643,"remaining_time":0.4320955891},
{"learn":[3.83969656],"iteration":534,"passed_time":0.4957169277,"remaining_time":0.430856769},
{"learn":[3.836811463],"iteration":535,"passed_time":0.4963050259,"remaining_time":0.4296371866},
{"learn":[3.834182551],"iteration":536,"passed_time":0.4968998172,"remaining_time":0.428425727},
{"learn":[3.828012842],"iteration":537,"passed_time":0.4975142205,"remaining_time":0.4272334012},
{"learn":[3.826636176],"iteration":538,"passed_time":0.4980677367,"remaining_time":0.425991144},
{"learn":[3.826189798],"iteration":539,"passed_time":0.4988212794,"remaining_time":0.4249218306},
{"learn":[3.824104738],"iteration":540,"passed_time":0.4994049685,"remaining_time":0.4237095759},
{"learn":[3.82300218],"iteration":541,"passed_time":0.5001294791,"remaining_time":0.4226186374},
{"learn":[3.817146402],"iteration":542,"passed_time":0.5007169058,"remaining_time":0.4214136758},
{"learn":[3.814638044],"iteration":543,"passed_time":0.5013457748,"remaining_time":0.420245723},
{"learn":[3.812979573],"iteration":544,"passed_time":0.5019418169,"remaining_time":0.4190523425},
{"learn":[3.811938825],"iteration":545,"passed_time":0.5025270682,"remaining_time":0.4178521776},
{"learn":[3.811479418],"iteration":546,"passed_time":0.5031964311,"remaining_time":0.4167239183},
{"learn":[3.80742981],"iteration":547,"passed_time":0.5038736077,"remaining_time":0.4156037786},
{"learn":[3.805097043],"iteration":548,"passed_time":0.5045702876,"remaining_time":0.4145012745},
{"learn":[3.801577232],"iteration":549,"passed_time":0.505188449,"remaining_time":0.4133360037},
{"learn":[3.799762083],"iteration":550,"passed_time":0.5057830196,"remaining_time":0.4121534951},
{"learn":[3.796393455],"iteration":551,"passed_time":0.5065092136,"remaining_time":0.4110799415},
{"learn":[3.793486459],"iteration":552,"passed_time":0.5071602952,"remaining_time":0.4099469294},
{"learn":[3.792006091],"iteration":553,"passed_time":0.5077817137,"remaining_time":0.4087917767},
{"learn":[3.78932128],"iteration":554,"passed_time":0.5084830144,"remaining_time":0.4077025972},
{"learn":[3.787581812],"iteration":555,"passed_time":0.5091352654,"remaining_time":0.4065756436},
{"learn":[3.785308865],"iteration":556,"passed_time":0.5097851334,"remaining_time":0.4054484992},
{"learn":[3.78465475],"iteration":557,"passed_time":0.5103357141,"remaining_time":0.4042444187},
{"learn":[3.780498869],"iteration":558,"passed_time":0.5109281886,"remaining_time":0.4030757266},
{"learn":[3.778734909],"iteration":559,"passed_time":0.5115253738,"remaining_time":0.4019127937},
{"learn":[3.778652349],"iteration":560,"passed_time":0.512093446,"remaining_time":0.4007290959},
{"learn":[3.777928006],"iteration":561,"passed_time":0.5127207225,"remaining_time":0.3995937304},
{"learn":[3.776131406],"iteration":562,"passed_time":0.5133454857,"remaining_time":0.3984582189},
{"learn":[3.772925617],"iteration":563,"passed_time":0.5141289317,"remaining_time":0.3974471883},
{"learn":[3.7727745],"iteration":564,"passed_time":0.5148075821,"remaining_time":0.39635628},
{"learn":[3.771763073],"iteration":565,"passed_time":0.5153840447,"remaining_time":0.3951884724},
{"learn":[3.768738162],"iteration":566,"passed_time":0.5160693704,"remaining_time":0.394105886},
{"learn":[3.767220794],"iteration":567,"passed_time":0.5167101712,"remaining_time":0.3929908345},
{"learn":[3.766691102],"iteration":568,"passed_time":0.5172584482,"remaining_time":0.3918073658},
{"learn":[3.766259335],"iteration":569,"passed_time":0.5178300767,"remaining_time":0.3906437421},
{"learn":[3.76116362],"iteration":570,"passed_time":0.5184076859,"remaining_time":0.3894866852},
{"learn":[3.758633056],"iteration":571,"passed_time":0.5190337022,"remaining_time":0.3883678751},
{"learn":[3.754603809],"iteration":572,"passed_time":0.5197819643,"remaining_time":0.3873418826},
{"learn":[3.754070549],"iteration":573,"passed_time":0.5204619359,"remaining_time":0.3862661754},
{"learn":[3.750534319],"iteration":574,"passed_time":0.5211366681,"remaining_time":0.3851879721},
{"learn":[3.746491516],"iteration":575,"passed_time":0.5218049589,"remaining_time":0.3841064281},
{"learn":[3.744210544],"iteration":576,"passed_time":0.5224693943,"remaining_time":0.3830234901},
{"learn":[3.742929991],"iteration":577,"passed_time":0.5231379571,"remaining_time":0.3819450136},
{"learn":[3.740402992],"iteration":578,"passed_time":0.5237738686,"remaining_time":0.3808442119},
{"learn":[3.739644243],"iteration":579,"passed_time":0.524422766,"remaining_time":0.3797544168},
{"learn":[3.737529404],"iteration":580,"passed_time":0.5250360889,"remaining_time":0.378640484},
{"learn":[3.737196923],"iteration":581,"passed_time":0.5256359662,"remaining_time":0.3775186149},
{"learn":[3.733954464],"iteration":582,"passed_time":0.5263972238,"remaining_time":0.3765139663},
{"learn":[3.731608623],"iteration":583,"passed_time":0.5269745125,"remaining_time":0.3753791048},
{"learn":[3.729843952],"iteration":584,"passed_time":0.5276029121,"remaining_time":0.3742824078},
{"learn":[3.727223798],"iteration":585,"passed_time":0.5281802123,"remaining_time":0.373151208},
{"learn":[3.725351667],"iteration":586,"passed_time":0.528722168,"remaining_time":0.3719970279},
{"learn":[3.725026912],"iteration":587,"passed_time":0.5293164387,"remaining_time":0.3708815863},
{"learn":[3.721974565],"iteration":588,"passed_time":0.5298617503,"remaining_time":0.3697337511},
{"learn":[3.720269493],"iteration":589,"passed_time":0.5305362734,"remaining_time":0.3686777493},
{"learn":[3.718907466],"iteration":590,"passed_time":0.5311897981,"remaining_time":0.3676085067},
{"learn":[3.715602912],"iteration":591,"passed_time":0.5318495437,"remaining_time":0.3665449558},
{"learn":[3.714463059],"iteration":592,"passed_time":0.5324854064,"remaining_time":0.365466375},
{"learn":[3.710802077],"iteration":593,"passed_time":0.5330861683,"remaining_time":0.3643652935},
{"learn":[3.708032435],"iteration":594,"passed_time":0.533717353,"remaining_time":0.3632866016},
{"learn":[3.703788939],"iteration":595,"passed_time":0.5343459029,"remaining_time":0.3622076255},
{"learn":[3.702500944],"iteration":596,"passed_time":0.5349691926,"remaining_time":0.3611266074},
{"learn":[3.698196925],"iteration":597,"passed_time":0.5356275071,"remaining_time":0.3600706653},
{"learn":[3.69658891],"iteration":598,"passed_time":0.5363019588,"remaining_time":0.3590268539},
{"learn":[3.696124066],"iteration":599,"passed_time":0.5369045671,"remaining_time":0.3579363781},
{"learn":[3.693537052],"iteration":600,"passed_time":0.5375978035,"remaining_time":0.3569076932},
{"learn":[3.691343275],"iteration":601,"passed_time":0.5382825849,"remaining_time":0.3558745329},
{"learn":[3.690973831],"iteration":602,"passed_time":0.5389651022,"remaining_time":0.3548410375},
{"learn":[3.686151073],"iteration":603,"passed_time":0.5396517961,"remaining_time":0.3538114425},
{"learn":[3.683921982],"iteration":604,"passed_time":0.5403208582,"remaining_time":0.3527714694},
{"learn":[3.679975271],"iteration":605,"passed_time":0.5409336616,"remaining_time":0.3516961431},
{"learn":[3.674047638],"iteration":606,"passed_time":0.5415336607,"remaining_time":0.3506140505},
{"learn":[3.673151794],"iteration":607,"passed_time":0.5421451117,"remaining_time":0.3495409273},
{"learn":[3.670953108],"iteration":608,"passed_time":0.5428931164,"remaining_time":0.3485569926},
{"learn":[3.6703947],"iteration":609,"passed_time":0.5434753538,"remaining_time":0.3474678491},
{"learn":[3.668433805],"iteration":610,"passed_time":0.5440777556,"remaining_time":0.3463932029},
{"learn":[3.668304956],"iteration":611,"passed_time":0.5447428207,"remaining_time":0.3453598275},
{"learn":[3.667880012],"iteration":612,"passed_time":0.5452780829,"remaining_time":0.3442457065},
{"learn":[3.667282264],"iteration":613,"passed_time":0.5458896426,"remaining_time":0.3431814365},
{"learn":[3.664611483],"iteration":614,"passed_time":0.546516902,"remaining_time":0.3421284671},
{"learn":[3.662543394],"iteration":615,"passed_time":0.5470704784,"remaining_time":0.3410309476},
{"learn":[3.659041959],"iteration":616,"passed_time":0.5476409333,"remaining_time":0.3399456685},
{"learn":[3.656868545],"iteration":617,"passed_time":0.5483054085,"remaining_time":0.3389201716},
{"learn":[3.654785614],"iteration":618,"passed_time":0.5490094931,"remaining_time":0.3379202211},
{"learn":[3.654566096],"iteration":619,"passed_time":0.5496081497,"remaining_time":0.3368566079},
{"learn":[3.651007045],"iteration":620,"passed_time":0.550213278,"remaining_time":0.3357984418},
{"learn":[3.648921786],"iteration":621,"passed_time":0.5508617722,"remaining_time":0.3347680867},
{"learn":[3.647655706],"iteration":622,"passed_time":0.5514950603,"remaining_time":0.3337297556},
{"learn":[3.647241144],"iteration":623,"passed_time":0.5521343509,"remaining_time":0.3326963397},
{"learn":[3.644195689],"iteration":624,"passed_time":0.5527733082,"remaining_time":0.3316639849},
{"learn":[3.642632246],"iteration":625,"passed_time":0.5533639704,"remaining_time":0.3306040334},
{"learn":[3.642523322],"iteration":626,"passed_time":0.5538348703,"remaining_time":0.3294743328},
{"learn":[3.641494659],"iteration":627,"passed_time":0.554417789,"remaining_time":0.3284130852},
{"learn":[3.63976496],"iteration":628,"passed_time":0.5550624076,"remaining_time":0.3273897507},
{"learn":[3.637945652],"iteration":629,"passed_time":0.5556922599,"remaining_time":0.3263589463},
{"learn":[3.636233667],"iteration":630,"passed_time":0.556350418,"remaining_time":0.3253459655},
{"learn":[3.635304404],"iteration":631,"passed_time":0.5569583012,"remaining_time":0.3243048336},
{"learn":[3.632234951],"iteration":632,"passed_time":0.5575808604,"remaining_time":0.3232735794},
{"learn":[3.631630987],"iteration":633,"passed_time":0.5582441122,"remaining_time":0.3222671058},
{"learn":[3.630301009],"iteration":634,"passed_time":0.5588334223,"remaining_time":0.3212192112},
{"learn":[3.629077964],"iteration":635,"passed_time":0.5594445002,"remaining_time":0.3201852171},
{"learn":[3.628004522],"iteration":636,"passed_time":0.5601021016,"remaining_time":0.3191790626},
{"learn":[3.625062876],"iteration":637,"passed_time":0.5607409714,"remaining_time":0.3181633725},
{"learn":[3.624917986],"iteration":638,"passed_time":0.5613049983,"remaining_time":0.3171065796},
{"learn":[3.622887087],"iteration":639,"passed_time":0.5619520111,"remaining_time":0.3160980062},
{"learn":[3.621220865],"iteration":640,"passed_time":0.5626514328,"remaining_time":0.3151199132},
{"learn":[3.621143844],"iteration":641,"passed_time":0.5632360299,"remaining_time":0.3140786584},
{"learn":[3.620822821],"iteration":642,"passed_time":0.5637753718,"remaining_time":0.3130136979},
{"learn":[3.619202826],"iteration":643,"passed_time":0.5643857995,"remaining_time":0.3119896655},
{"learn":[3.618204882],"iteration":644,"passed_time":0.5649727899,"remaining_time":0.3109540162},
{"learn":[3.614259666],"iteration":645,"passed_time":0.5655919522,"remaining_time":0.3099373856},
{"learn":[3.613415661],"iteration":646,"passed_time":0.5662239283,"remaining_time":0.3089289748},
{"learn":[3.611096773],"iteration":647,"passed_time":0.5668182284,"remaining_time":0.3079012599},
{"learn":[3.610820695],"iteration":648,"passed_time":0.567367417,"remaining_time":0.3068504828},
{"learn":[3.609290065],"iteration":649,"passed_time":0.5679922203,"remaining_time":0.3058419648},
{"learn":[3.60897947],"iteration":650,"passed_time":0.5686733393,"remaining_time":0.3048648163},
{"learn":[3.606570702],"iteration":651,"passed_time":0.5693302954,"remaining_time":0.3038756791},
{"learn":[3.606292637],"iteration":652,"passed_time":0.5699510815,"remaining_time":0.3028683389},
{"learn":[3.602753838],"iteration":653,"passed_time":0.5705297529,"remaining_time":0.3018398998},
{"learn":[3.599755869],"iteration":654,"passed_time":0.5711504088,"remaining_time":0.3008349481},
{"learn":[3.599509575],"iteration":655,"passed_time":0.5718650609,"remaining_time":0.2998804588},
{"learn":[3.595337722],"iteration":656,"passed_time":0.5724779846,"remaining_time":0.2988735901},
{"learn":[3.595168561],"iteration":657,"passed_time":0.5731033974,"remaining_time":0.2978744102},
{"learn":[3.59290559],"iteration":658,"passed_time":0.5737933571,"remaining_time":0.2969097644},
{"learn":[3.592015928],"iteration":659,"passed_time":0.5744141232,"remaining_time":0.2959103059},
{"learn":[3.590680403],"iteration":660,"passed_time":0.5750354518,"remaining_time":0.2949122816},
{"learn":[3.590361532],"iteration":661,"passed_time":0.5755870045,"remaining_time":0.2938797697},
{"learn":[3.589069739],"iteration":662,"passed_time":0.5761904009,"remaining_time":0.2928750605},
{"learn":[3.585010186],"iteration":663,"passed_time":0.5768482731,"remaining_time":0.2918991261},
{"learn":[3.582997552],"iteration":664,"passed_time":0.5774198014,"remaining_time":0.2908806519},
{"learn":[3.582119256],"iteration":665,"passed_time":0.5780091227,"remaining_time":0.2898724429},
{"learn":[3.579019356],"iteration":666,"passed_time":0.5786550658,"remaining_time":0.2888937585},
{"learn":[3.57719559],"iteration":667,"passed_time":0.5792981717,"remaining_time":0.2879146602},
{"learn":[3.574050046],"iteration":668,"passed_time":0.5798331148,"remaining_time":0.2868830508},
{"learn":[3.572204518],"iteration":669,"passed_time":0.5805889829,"remaining_time":0.2859617378},
{"learn":[3.569508025],"iteration":670,"passed_time":0.5812349126,"remaining_time":0.2849870138},
{"learn":[3.566268704],"iteration":671,"passed_time":0.58186206,"remaining_time":0.2840041007},
{"learn":[3.562564052],"iteration":672,"passed_time":0.5824921342,"remaining_time":0.283023667},
{"learn":[3.561173586],"iteration":673,"passed_time":0.5830974327,"remaining_time":0.2820322894},
{"learn":[3.559551904],"iteration":674,"passed_time":0.5837871101,"remaining_time":0.2810826826},
{"learn":[3.558593054],"iteration":675,"passed_time":0.5844858369,"remaining_time":0.2801381822},
{"learn":[3.555647008],"iteration":676,"passed_time":0.5851308662,"remaining_time":0.2791687885},
{"learn":[3.553100059],"iteration":677,"passed_time":0.585710489,"remaining_time":0.2781692883},
{"learn":[3.55085578],"iteration":678,"passed_time":0.5862925173,"remaining_time":0.2771721621},
{"learn":[3.550737965],"iteration":679,"passed_time":0.586863294,"remaining_time":0.2761709619},
{"learn":[3.549408772],"iteration":680,"passed_time":0.5875077927,"remaining_time":0.2752055593},
{"learn":[3.547390589],"iteration":681,"passed_time":0.5881726161,"remaining_time":0.2742505746},
{"learn":[3.54723575],"iteration":682,"passed_time":0.5887363189,"remaining_time":0.2732495067},
{"learn":[3.543988891],"iteration":683,"passed_time":0.5893866981,"remaining_time":0.2722897611},
{"learn":[3.543868508],"iteration":684,"passed_time":0.5899391124,"remaining_time":0.2712858692},
{"learn":[3.542752124],"iteration":685,"passed_time":0.5905611307,"remaining_time":0.2703151531},
{"learn":[3.541334315],"iteration":686,"passed_time":0.5912012413,"remaining_time":0.2693536951},
{"learn":[3.540208266],"iteration":687,"passed_time":0.5918007297,"remaining_time":0.2683747495},
{"learn":[3.537730983],"iteration":688,"passed_time":0.5923727805,"remaining_time":0.2673845207},
{"learn":[3.53419867],"iteration":689,"passed_time":0.5929240228,"remaining_time":0.2663861551},
{"learn":[3.532628335],"iteration":690,"passed_time":0.5935356741,"remaining_time":0.2654160974},
{"learn":[3.532204987],"iteration":691,"passed_time":0.5941398394,"remaining_time":0.2644437436},
{"learn":[3.530618147],"iteration":692,"passed_time":0.5947487844,"remaining_time":0.2634745697},
{"learn":[3.528909306],"iteration":693,"passed_time":0.5954105448,"remaining_time":0.2625297215},
{"learn":[3.526700678],"iteration":694,"passed_time":0.5962194005,"remaining_time":0.2616502405},
{"learn":[3.526439574],"iteration":695,"passed_time":0.5967874081,"remaining_time":0.2606657644},
{"learn":[3.525784216],"iteration":696,"passed_time":0.5974872751,"remaining_time":0.2597398054},
{"learn":[3.524112693],"iteration":697,"passed_time":0.5981291106,"remaining_time":0.2587893859},
{"learn":[3.522813541],"iteration":698,"passed_time":0.5986912321,"remaining_time":0.2578055234},
{"learn":[3.519148203],"iteration":699,"passed_time":0.5994695144,"remaining_time":0.2569155062},
{"learn":[3.517236747],"iteration":700,"passed_time":0.600155027,"remaining_time":0.2559862383},
{"learn":[3.515603888],"iteration":701,"passed_time":0.6008779263,"remaining_time":0.2550735357},
{"learn":[3.51263524],"iteration":702,"passed_time":0.6015372924,"remaining_time":0.2541345318},
{"learn":[3.51123442],"iteration":703,"passed_time":0.6021405476,"remaining_time":0.2531727302},
{"learn":[3.50828027],"iteration":704,"passed_time":0.602723859,"remaining_time":0.2522036006},
{"learn":[3.508265537],"iteration":705,"passed_time":0.6032015289,"remaining_time":0.2511915715},
{"learn":[3.506774876],"iteration":706,"passed_time":0.6038871506,"remaining_time":0.250267235},
{"learn":[3.50552068],"iteration":707,"passed_time":0.6044262724,"remaining_time":0.2492831519},
{"learn":[3.501973993],"iteration":708,"passed_time":0.6050779351,"remaining_time":0.248346515},
{"learn":[3.498880354],"iteration":709,"passed_time":0.6058141268,"remaining_time":0.2474452067},
{"learn":[3.497370959],"iteration":710,"passed_time":0.6065199144,"remaining_time":0.2465320046},
{"learn":[3.496050455],"iteration":711,"passed_time":0.60721833,"remaining_time":0.2456164032},
{"learn":[3.495630067],"iteration":712,"passed_time":0.6078216966,"remaining_time":0.2446631514},
{"learn":[3.49550669],"iteration":713,"passed_time":0.6084557865,"remaining_time":0.2437231862},
{"learn":[3.493652375],"iteration":714,"passed_time":0.6090590714,"remaining_time":0.2427717977},
{"learn":[3.491915684],"iteration":715,"passed_time":0.6097237557,"remaining_time":0.2418457355},
{"learn":[3.490303956],"iteration":716,"passed_time":0.6104755474,"remaining_time":0.2409547837},
{"learn":[3.488363853],"iteration":717,"passed_time":0.6110876581,"remaining_time":0.2400093587},
{"learn":[3.485483936],"iteration":718,"passed_time":0.6116900514,"remaining_time":0.2390610632},
{"learn":[3.483763466],"iteration":719,"passed_time":0.6122663896,"remaining_time":0.2381035959},
{"learn":[3.481642352],"iteration":720,"passed_time":0.6129023318,"remaining_time":0.2371702504},
{"learn":[3.479826119],"iteration":721,"passed_time":0.6135969191,"remaining_time":0.2362603096},
{"learn":[3.478588728],"iteration":722,"passed_time":0.614246607,"remaining_time":0.2353337623},
{"learn":[3.475390887],"iteration":723,"passed_time":0.6148408844,"remaining_time":0.2343868565},
{"learn":[3.472636852],"iteration":724,"passed_time":0.6154012425,"remaining_time":0.2334280575},
{"learn":[3.47061883],"iteration":725,"passed_time":0.6159528254,"remaining_time":0.2324670443},
{"learn":[3.46953149],"iteration":726,"passed_time":0.6165724297,"remaining_time":0.2315327006},
{"learn":[3.467217162],"iteration":727,"passed_time":0.6171939975,"remaining_time":0.2305999551},
{"learn":[3.465686216],"iteration":728,"passed_time":0.6177978935,"remaining_time":0.229661494},
{"learn":[3.462631216],"iteration":729,"passed_time":0.6184871617,"remaining_time":0.2287555255},
{"learn":[3.461451053],"iteration":730,"passed_time":0.6190696095,"remaining_time":0.2278108412},
{"learn":[3.458950469],"iteration":731,"passed_time":0.6197680625,"remaining_time":0.2269096185},
{"learn":[3.458072145],"iteration":732,"passed_time":0.6205334362,"remaining_time":0.2260333253},
{"learn":[3.454364268],"iteration":733,"passed_time":0.621174344,"remaining_time":0.2251122282},
{"learn":[3.453243406],"iteration":734,"passed_time":0.6217484669,"remaining_time":0.2241678146},
{"learn":[3.453017963],"iteration":735,"passed_time":0.6223143106,"remaining_time":0.2232214375},
{"learn":[3.45201581],"iteration":736,"passed_time":0.622977923,"remaining_time":0.222310982},
{"learn":[3.449510107],"iteration":737,"passed_time":0.6237344365,"remaining_time":0.2214341766},
{"learn":[3.447189189],"iteration":738,"passed_time":0.6244190418,"remaining_time":0.2205323003},
{"learn":[3.446423605],"iteration":739,"passed_time":0.6250888652,"remaining_time":0.2196258175},
{"learn":[3.445531987],"iteration":740,"passed_time":0.6258102218,"remaining_time":0.2187379857},
{"learn":[3.445328199],"iteration":741,"passed_time":0.6264634958,"remaining_time":0.2178269298},
{"learn":[3.443327544],"iteration":742,"passed_time":0.6270782812,"remaining_time":0.2169032547},
{"learn":[3.441475798],"iteration":743,"passed_time":0.627685403,"remaining_time":0.2159777731},
{"learn":[3.439046501],"iteration":744,"passed_time":0.628300519,"remaining_time":0.2150558823},
{"learn":[3.435899469],"iteration":745,"passed_time":0.6289578105,"remaining_time":0.2141491741},
{"learn":[3.433988352],"iteration":746,"passed_time":0.6295876115,"remaining_time":0.2132338229},
{"learn":[3.433413263],"iteration":747,"passed_time":0.6305604254,"remaining_time":0.2124347957},
{"learn":[3.429944699],"iteration":748,"passed_time":0.6317678623,"remaining_time":0.2117139298},
{"learn":[3.429291634],"iteration":749,"passed_time":0.6324231745,"remaining_time":0.2108077248},
{"learn":[3.429175603],"iteration":750,"passed_time":0.6330472765,"remaining_time":0.20989184},
{"learn":[3.428780323],"iteration":751,"passed_time":0.6337741917,"remaining_time":0.2090106377},
{"learn":[3.423893341],"iteration":752,"passed_time":0.6344583007,"remaining_time":0.2081158038},
{"learn":[3.421024316],"iteration":753,"passed_time":0.6350507363,"remaining_time":0.2071916195},
{"learn":[3.420969872],"iteration":754,"passed_time":0.6357336868,"remaining_time":0.2062976865},
{"learn":[3.419544785],"iteration":755,"passed_time":0.6366117823,"remaining_time":0.2054672948},
{"learn":[3.417057977],"iteration":756,"passed_time":0.6372955407,"remaining_time":0.2045743942},
{"learn":[3.415160245],"iteration":757,"passed_time":0.6379291596,"remaining_time":0.2036660378},
{"learn":[3.412854597],"iteration":758,"passed_time":0.6385563535,"remaining_time":0.2027563652},
{"learn":[3.410926347],"iteration":759,"passed_time":0.6393544954,"remaining_time":0.2019014196},
{"learn":[3.408963843],"iteration":760,"passed_time":0.6401839287,"remaining_time":0.2010564507},
{"learn":[3.407629634],"iteration":761,"passed_time":0.6408100944,"remaining_time":0.2001480347},
{"learn":[3.404384724],"iteration":762,"passed_time":0.641558508,"remaining_time":0.1992783308},
{"learn":[3.403041656],"iteration":763,"passed_time":0.6421844132,"remaining_time":0.1983711015},
{"learn":[3.401101731],"iteration":764,"passed_time":0.6428612392,"remaining_time":0.1974802499},
{"learn":[3.400890668],"iteration":765,"passed_time":0.6435979707,"remaining_time":0.1966082574},
{"learn":[3.399289941],"iteration":766,"passed_time":0.6442443023,"remaining_time":0.1957091557},
{"learn":[3.399202366],"iteration":767,"passed_time":0.6449222913,"remaining_time":0.1948202755},
{"learn":[3.397447845],"iteration":768,"passed_time":0.6458216137,"remaining_time":0.1939984301},
{"learn":[3.394655341],"iteration":769,"passed_time":0.6466253874,"remaining_time":0.193147843},
{"learn":[3.393228229],"iteration":770,"passed_time":0.647243629,"remaining_time":0.1922422711},
{"learn":[3.389691197],"iteration":771,"passed_time":0.6479697027,"remaining_time":0.1913692904},
{"learn":[3.389626772],"iteration":772,"passed_time":0.648628064,"remaining_time":0.1904768053},
{"learn":[3.388480222],"iteration":773,"passed_time":0.6493172735,"remaining_time":0.1895939326},
{"learn":[3.388215066],"iteration":774,"passed_time":0.6501106025,"remaining_time":0.1887417878},
{"learn":[3.386324358],"iteration":775,"passed_time":0.650840483,"remaining_time":0.1878714796},
{"learn":[3.383913061],"iteration":776,"passed_time":0.6515956085,"remaining_time":0.1870087782},
{"learn":[3.382839768],"iteration":777,"passed_time":0.6526430048,"remaining_time":0.186229752},
{"learn":[3.381961844],"iteration":778,"passed_time":0.6533775636,"remaining_time":0.1853612857},
{"learn":[3.381521703],"iteration":779,"passed_time":0.6541322684,"remaining_time":0.1844988449},
{"learn":[3.380918963],"iteration":780,"passed_time":0.6548136925,"remaining_time":0.1836161315},
{"learn":[3.377139006],"iteration":781,"passed_time":0.6555482799,"remaining_time":0.1827487532},
{"learn":[3.376004372],"iteration":782,"passed_time":0.6561564954,"remaining_time":0.1818466916},
{"learn":[3.373826468],"iteration":783,"passed_time":0.6568707366,"remaining_time":0.1809745907},
{"learn":[3.373546786],"iteration":784,"passed_time":0.657549958,"remaining_time":0.1800933006},
{"learn":[3.372109181],"iteration":785,"passed_time":0.658165044,"remaining_time":0.1791950629},
{"learn":[3.370764924],"iteration":786,"passed_time":0.6589511547,"remaining_time":0.1783438322},
{"learn":[3.367833107],"iteration":787,"passed_time":0.6595508244,"remaining_time":0.1774426076},
{"learn":[3.36450404],"iteration":788,"passed_time":0.6601304074,"remaining_time":0.1765367756},
{"learn":[3.361794558],"iteration":789,"passed_time":0.6608738205,"remaining_time":0.1756753194},
{"learn":[3.356880529],"iteration":790,"passed_time":0.6615426422,"remaining_time":0.1747944529},
{"learn":[3.353843509],"iteration":791,"passed_time":0.6622080694,"remaining_time":0.1739132303},
{"learn":[3.353640253],"iteration":792,"passed_time":0.6627575084,"remaining_time":0.1730022752},
{"learn":[3.353055088],"iteration":793,"passed_time":0.6633466093,"remaining_time":0.1721025208},
{"learn":[3.351415617],"iteration":794,"passed_time":0.6639334971,"remaining_time":0.1712029772},
{"learn":[3.349169061],"iteration":795,"passed_time":0.6647085068,"remaining_time":0.1703524314},
{"learn":[3.346211014],"iteration":796,"passed_time":0.6654656471,"remaining_time":0.1694975237},
{"learn":[3.344560452],"iteration":797,"passed_time":0.6661209663,"remaining_time":0.1686170867},
{"learn":[3.344445461],"iteration":798,"passed_time":0.6667503277,"remaining_time":0.1677306832},
{"learn":[3.342608898],"iteration":799,"passed_time":0.6673216657,"remaining_time":0.1668304164},
{"learn":[3.339572899],"iteration":800,"passed_time":0.6680218433,"remaining_time":0.1659629798},
{"learn":[3.339309302],"iteration":801,"passed_time":0.6686080778,"remaining_time":0.1650678297},
{"learn":[3.33698088],"iteration":802,"passed_time":0.6691816453,"remaining_time":0.1641703414},
{"learn":[3.334746342],"iteration":803,"passed_time":0.6698266036,"remaining_time":0.1632910626},
{"learn":[3.332048511],"iteration":804,"passed_time":0.670376844,"remaining_time":0.1623894218},
{"learn":[3.331932544],"iteration":805,"passed_time":0.6709376933,"remaining_time":0.1614912066},
{"learn":[3.330541133],"iteration":806,"passed_time":0.6714919797,"remaining_time":0.1605922579},
{"learn":[3.329124989],"iteration":807,"passed_time":0.6720392649,"remaining_time":0.1596924986},
{"learn":[3.32583918],"iteration":808,"passed_time":0.6726112941,"remaining_time":0.1587994526},
{"learn":[3.325287299],"iteration":809,"passed_time":0.6732455543,"remaining_time":0.1579217967},
{"learn":[3.322745162],"iteration":810,"passed_time":0.673883225,"remaining_time":0.1570455358},
{"learn":[3.319733662],"iteration":811,"passed_time":0.6744760113,"remaining_time":0.1561594706},
{"learn":[3.318080007],"iteration":812,"passed_time":0.6751992208,"remaining_time":0.1553041258},
{"learn":[3.317179538],"iteration":813,"passed_time":0.6759135849,"remaining_time":0.1544470845},
{"learn":[3.315685949],"iteration":814,"passed_time":0.6765236537,"remaining_time":0.1535667189},
{"learn":[3.314944576],"iteration":815,"passed_time":0.6771081272,"remaining_time":0.1526812444},
{"learn":[3.312369052],"iteration":816,"passed_time":0.6777813887,"remaining_time":0.1518163943},
{"learn":[3.312321621],"iteration":817,"passed_time":0.6782481115,"remaining_time":0.150906059},
{"learn":[3.309465776],"iteration":818,"passed_time":0.6788856575,"remaining_time":0.1500345592},
{"learn":[3.308307377],"iteration":819,"passed_time":0.6795197895,"remaining_time":0.1491628806},
{"learn":[3.308076804],"iteration":820,"passed_time":0.6802879082,"remaining_time":0.1483209934},
{"learn":[3.305643326],"iteration":821,"passed_time":0.6810034143,"remaining_time":0.1474678926},
{"learn":[3.304154814],"iteration":822,"passed_time":0.6819917453,"remaining_time":0.1466738018},
{"learn":[3.303076321],"iteration":823,"passed_time":0.6825858539,"remaining_time":0.1457950367},
{"learn":[3.301746372],"iteration":824,"passed_time":0.6831187935,"remaining_time":0.1449039865},
{"learn":[3.301345455],"iteration":825,"passed_time":0.6837119804,"remaining_time":0.1440264947},
{"learn":[3.299181039],"iteration":826,"passed_time":0.6843069627,"remaining_time":0.143150066},
{"learn":[3.297989357],"iteration":827,"passed_time":0.6849255352,"remaining_time":0.1422792174},
{"learn":[3.294775182],"iteration":828,"passed_time":0.6855220796,"remaining_time":0.1414044338},
{"learn":[3.293840636],"iteration":829,"passed_time":0.6860938884,"remaining_time":0.1405252543},
{"learn":[3.289279397],"iteration":830,"passed_time":0.6866929944,"remaining_time":0.1396523659},
{"learn":[3.286204979],"iteration":831,"passed_time":0.6872737204,"remaining_time":0.1387764243},
{"learn":[3.284833593],"iteration":832,"passed_time":0.6879482608,"remaining_time":0.1379199995},
{"learn":[3.283519914],"iteration":833,"passed_time":0.6885238263,"remaining_time":0.1370443108},
{"learn":[3.282853026],"iteration":834,"passed_time":0.6891050419,"remaining_time":0.1361704574},
{"learn":[3.281944673],"iteration":835,"passed_time":0.6896865772,"remaining_time":0.1352973668},
{"learn":[3.279764865],"iteration":836,"passed_time":0.6902619724,"remaining_time":0.1344237772},
{"learn":[3.277468839],"iteration":837,"passed_time":0.6908297842,"remaining_time":0.1335494332},
{"learn":[3.277124974],"iteration":838,"passed_time":0.6914880425,"remaining_time":0.1326931762},
{"learn":[3.275636037],"iteration":839,"passed_time":0.692095575,"remaining_time":0.1318277286},
{"learn":[3.274413635],"iteration":840,"passed_time":0.6927250178,"remaining_time":0.1309670367},
{"learn":[3.272636087],"iteration":841,"passed_time":0.6932980585,"remaining_time":0.1300963103},
{"learn":[3.269644466],"iteration":842,"passed_time":0.6939180044,"remaining_time":0.1292350257},
{"learn":[3.26852083],"iteration":843,"passed_time":0.6947320846,"remaining_time":0.1284101957},
{"learn":[3.267820927],"iteration":844,"passed_time":0.6953766832,"remaining_time":0.1275543028},
{"learn":[3.267331099],"iteration":845,"passed_time":0.6960440511,"remaining_time":0.1267030542},
{"learn":[3.267231014],"iteration":846,"passed_time":0.6966756064,"remaining_time":0.1258457707},
{"learn":[3.267158695],"iteration":847,"passed_time":0.6973133142,"remaining_time":0.1249901224},
{"learn":[3.264718705],"iteration":848,"passed_time":0.6978879981,"remaining_time":0.1241237782},
{"learn":[3.261678512],"iteration":849,"passed_time":0.6985051593,"remaining_time":0.1232656164},
{"learn":[3.261368381],"iteration":850,"passed_time":0.6990999081,"remaining_time":0.1224040967},
{"learn":[3.260128799],"iteration":851,"passed_time":0.6997372522,"remaining_time":0.1215506025},
{"learn":[3.258972952],"iteration":852,"passed_time":0.700349994,"remaining_time":0.1206933753},
{"learn":[3.258724846],"iteration":853,"passed_time":0.7010559216,"remaining_time":0.1198526517},
{"learn":[3.25686724],"iteration":854,"passed_time":0.7016313068,"remaining_time":0.1189901047},
{"learn":[3.255750259],"iteration":855,"passed_time":0.7022146677,"remaining_time":0.1181295703},
{"learn":[3.254915866],"iteration":856,"passed_time":0.7028105483,"remaining_time":0.1172717718},
{"learn":[3.254348625],"iteration":857,"passed_time":0.7033707349,"remaining_time":0.1164086764},
{"learn":[3.253408514],"iteration":858,"passed_time":0.7040499852,"remaining_time":0.1155658299},
{"learn":[3.253291714],"iteration":859,"passed_time":0.7046267329,"remaining_time":0.1147066774},
{"learn":[3.250186342],"iteration":860,"passed_time":0.7052621062,"remaining_time":0.1138576455},
{"learn":[3.249141318],"iteration":861,"passed_time":0.7058494943,"remaining_time":0.1130014272},
{"learn":[3.246300388],"iteration":862,"passed_time":0.7065425947,"remaining_time":0.1121626135},
{"learn":[3.245205135],"iteration":863,"passed_time":0.707201058,"remaining_time":0.1113186851},
{"learn":[3.244403535],"iteration":864,"passed_time":0.7078895948,"remaining_time":0.110479879},
{"learn":[3.244211781],"iteration":865,"passed_time":0.7085495808,"remaining_time":0.1096370021},
{"learn":[3.242286347],"iteration":866,"passed_time":0.7094131796,"remaining_time":0.1088257819},
{"learn":[3.239606746],"iteration":867,"passed_time":0.7101394837,"remaining_time":0.107993562},
{"learn":[3.236773361],"iteration":868,"passed_time":0.710814226,"remaining_time":0.1071538131},
{"learn":[3.234552446],"iteration":869,"passed_time":0.7114258461,"remaining_time":0.1063050115},
{"learn":[3.233724647],"iteration":870,"passed_time":0.7119936478,"remaining_time":0.1054502647},
{"learn":[3.230851485],"iteration":871,"passed_time":0.7126444883,"remaining_time":0.1046083653},
{"learn":[3.227728941],"iteration":872,"passed_time":0.7132722381,"remaining_time":0.1037635444},
{"learn":[3.225787575],"iteration":873,"passed_time":0.713855889,"remaining_time":0.1029128627},
{"learn":[3.222797487],"iteration":874,"passed_time":0.7145441508,"remaining_time":0.1020777358},
{"learn":[3.22137014],"iteration":875,"passed_time":0.7151795441,"remaining_time":0.1012354606},
{"learn":[3.219701963],"iteration":876,"passed_time":0.7157788805,"remaining_time":0.1003886001},
{"learn":[3.21783327],"iteration":877,"passed_time":0.7164512097,"remaining_time":0.09955244599},
{"learn":[3.217713355],"iteration":878,"passed_time":0.7170498078,"remaining_time":0.09870651506},
{"learn":[3.217666091],"iteration":879,"passed_time":0.7176736072,"remaining_time":0.09786458279},
{"learn":[3.214962005],"iteration":880,"passed_time":0.718497657,"remaining_time":0.0970501943},
{"learn":[3.214081828],"iteration":881,"passed_time":0.7192510008,"remaining_time":0.09622632437},
{"learn":[3.213358337],"iteration":882,"passed_time":0.7199419522,"remaining_time":0.09539434701},
{"learn":[3.210850401],"iteration":883,"passed_time":0.7206205611,"remaining_time":0.0945610691},
{"learn":[3.207810328],"iteration":884,"passed_time":0.7212546594,"remaining_time":0.09372235687},
{"learn":[3.204935073],"iteration":885,"passed_time":0.721848649,"remaining_time":0.09287894581},
{"learn":[3.20280198],"iteration":886,"passed_time":0.72245534,"remaining_time":0.09203771524},
{"learn":[3.200663495],"iteration":887,"passed_time":0.7230703458,"remaining_time":0.09119806164},
{"learn":[3.197301669],"iteration":888,"passed_time":0.7236658269,"remaining_time":0.09035647557},
{"learn":[3.195666943],"iteration":889,"passed_time":0.7242703452,"remaining_time":0.08951655952},
{"learn":[3.193886506],"iteration":890,"passed_time":0.7247875568,"remaining_time":0.08866649123},
{"learn":[3.190601248],"iteration":891,"passed_time":0.7254123755,"remaining_time":0.08783019794},
{"learn":[3.188983797],"iteration":892,"passed_time":0.7260336726,"remaining_time":0.08699395629},
{"learn":[3.187365749],"iteration":893,"passed_time":0.7267048776,"remaining_time":0.08616411301},
{"learn":[3.186160771],"iteration":894,"passed_time":0.7272898399,"remaining_time":0.08532450636},
{"learn":[3.185358981],"iteration":895,"passed_time":0.7279074817,"remaining_time":0.08448926126},
{"learn":[3.183832164],"iteration":896,"passed_time":0.7284973818,"remaining_time":0.08365131586},
{"learn":[3.183106966],"iteration":897,"passed_time":0.7291349479,"remaining_time":0.08281933706},
{"learn":[3.182838152],"iteration":898,"passed_time":0.7297517068,"remaining_time":0.08198545316},
{"learn":[3.180835453],"iteration":899,"passed_time":0.730448318,"remaining_time":0.08116092423},
{"learn":[3.179957348],"iteration":900,"passed_time":0.7310799535,"remaining_time":0.08032953984},
{"learn":[3.179752966],"iteration":901,"passed_time":0.731704598,"remaining_time":0.07949783881},
{"learn":[3.178851983],"iteration":902,"passed_time":0.7323347123,"remaining_time":0.07866718393},
{"learn":[3.176748586],"iteration":903,"passed_time":0.732953296,"remaining_time":0.07783574824},
{"learn":[3.172960988],"iteration":904,"passed_time":0.7336045564,"remaining_time":0.0770082131},
{"learn":[3.172794225],"iteration":905,"passed_time":0.7342145132,"remaining_time":0.07617678172},
{"learn":[3.169996507],"iteration":906,"passed_time":0.7347896793,"remaining_time":0.07534227141},
{"learn":[3.16813015],"iteration":907,"passed_time":0.7353842487,"remaining_time":0.07451029832},
{"learn":[3.166920871],"iteration":908,"passed_time":0.7359974221,"remaining_time":0.07368071003},
{"learn":[3.16531606],"iteration":909,"passed_time":0.7366414897,"remaining_time":0.07285465283},
{"learn":[3.162035247],"iteration":910,"passed_time":0.7373169433,"remaining_time":0.07203206142},
{"learn":[3.16189467],"iteration":911,"passed_time":0.7379420583,"remaining_time":0.07120493545},
{"learn":[3.161008416],"iteration":912,"passed_time":0.7385358075,"remaining_time":0.07037526314},
{"learn":[3.160560787],"iteration":913,"passed_time":0.7390472803,"remaining_time":0.06953836555},
{"learn":[3.160416261],"iteration":914,"passed_time":0.7396124373,"remaining_time":0.06870716631},
{"learn":[3.15844291],"iteration":915,"passed_time":0.7402738571,"remaining_time":0.06788537554},
{"learn":[3.155040501],"iteration":916,"passed_time":0.7408920902,"remaining_time":0.06706002561},
{"learn":[3.154937548],"iteration":917,"passed_time":0.7414866896,"remaining_time":0.06623301585},
{"learn":[3.153721161],"iteration":918,"passed_time":0.742113953,"remaining_time":0.06540939086},
{"learn":[3.153170511],"iteration":919,"passed_time":0.7427663254,"remaining_time":0.06458837613},
{"learn":[3.153113601],"iteration":920,"passed_time":0.7433675069,"remaining_time":0.06376333664},
{"learn":[3.150607379],"iteration":921,"passed_time":0.743958982,"remaining_time":0.0629379616},
{"learn":[3.148408359],"iteration":922,"passed_time":0.7445736889,"remaining_time":0.06211503146},
{"learn":[3.147495728],"iteration":923,"passed_time":0.7451425825,"remaining_time":0.06128878384},
{"learn":[3.146946235],"iteration":924,"passed_time":0.7457222967,"remaining_time":0.06046397},
{"learn":[3.14472738],"iteration":925,"passed_time":0.7463958769,"remaining_time":0.0596471867},
{"learn":[3.144469477],"iteration":926,"passed_time":0.7469931711,"remaining_time":0.05882470495},
{"learn":[3.142975516],"iteration":927,"passed_time":0.7476135265,"remaining_time":0.05800449774},
{"learn":[3.14079113],"iteration":928,"passed_time":0.7482039184,"remaining_time":0.0571824308},
{"learn":[3.138173032],"iteration":929,"passed_time":0.748747487,"remaining_time":0.05635733773},
{"learn":[3.136352813],"iteration":930,"passed_time":0.7494161778,"remaining_time":0.05554212274},
{"learn":[3.133735004],"iteration":931,"passed_time":0.7500943116,"remaining_time":0.05472791115},
{"learn":[3.1319496],"iteration":932,"passed_time":0.7507826293,"remaining_time":0.05391472257},
{"learn":[3.129865343],"iteration":933,"passed_time":0.7514025624,"remaining_time":0.05309696907},
{"learn":[3.129830206],"iteration":934,"passed_time":0.7519067061,"remaining_time":0.05227158919},
{"learn":[3.126676562],"iteration":935,"passed_time":0.7525904244,"remaining_time":0.05145917431},
{"learn":[3.12645665],"iteration":936,"passed_time":0.7532566068,"remaining_time":0.0506458551},
{"learn":[3.126378007],"iteration":937,"passed_time":0.7538701901,"remaining_time":0.04982937291},
{"learn":[3.124621914],"iteration":938,"passed_time":0.7544813703,"remaining_time":0.04901316676},
{"learn":[3.123379018],"iteration":939,"passed_time":0.7550637192,"remaining_time":0.04819555654},
{"learn":[3.123332451],"iteration":940,"passed_time":0.7556648703,"remaining_time":0.04737962524},
{"learn":[3.122432444],"iteration":941,"passed_time":0.7563888919,"remaining_time":0.04657171521},
{"learn":[3.121889006],"iteration":942,"passed_time":0.7570023449,"remaining_time":0.04575729975},
{"learn":[3.121070914],"iteration":943,"passed_time":0.7576057185,"remaining_time":0.04494271212},
{"learn":[3.118444705],"iteration":944,"passed_time":0.7582552358,"remaining_time":0.04413125711},
{"learn":[3.116820458],"iteration":945,"passed_time":0.7589055345,"remaining_time":0.04332018908},
{"learn":[3.114971041],"iteration":946,"passed_time":0.7596465139,"remaining_time":0.04251453563},
{"learn":[3.114685138],"iteration":947,"passed_time":0.760318912,"remaining_time":0.04170525678},
{"learn":[3.113399363],"iteration":948,"passed_time":0.7609526567,"remaining_time":0.04089418914},
{"learn":[3.110575399],"iteration":949,"passed_time":0.7615957726,"remaining_time":0.04008398803},
{"learn":[3.110466553],"iteration":950,"passed_time":0.7621062919,"remaining_time":0.03926730631},
{"learn":[3.108691641],"iteration":951,"passed_time":0.7628236556,"remaining_time":0.03846169692},
{"learn":[3.107898017],"iteration":952,"passed_time":0.7634363473,"remaining_time":0.03765111052},
{"learn":[3.105551729],"iteration":953,"passed_time":0.7640250578,"remaining_time":0.03683978266},
{"learn":[3.104824945],"iteration":954,"passed_time":0.7647374784,"remaining_time":0.03603475029},
{"learn":[3.103186704],"iteration":955,"passed_time":0.7655584312,"remaining_time":0.03523490687},
{"learn":[3.102330655],"iteration":956,"passed_time":0.7662418604,"remaining_time":0.03442884012},
{"learn":[3.102291298],"iteration":957,"passed_time":0.7668805496,"remaining_time":0.03362106794},
{"learn":[3.100363529],"iteration":958,"passed_time":0.7675508051,"remaining_time":0.03281499793},
{"learn":[3.097871596],"iteration":959,"passed_time":0.7681892008,"remaining_time":0.03200788337},
{"learn":[3.097372213],"iteration":960,"passed_time":0.7687624635,"remaining_time":0.03119847667},
{"learn":[3.095981813],"iteration":961,"passed_time":0.7694580325,"remaining_time":0.03039439214},
{"learn":[3.095347452],"iteration":962,"passed_time":0.77012445,"remaining_time":0.02958941293},
{"learn":[3.094728409],"iteration":963,"passed_time":0.7707867391,"remaining_time":0.02878456702},
{"learn":[3.094118537],"iteration":964,"passed_time":0.7713739855,"remaining_time":0.02797729481},
{"learn":[3.093793695],"iteration":965,"passed_time":0.7720194957,"remaining_time":0.02717252883},
{"learn":[3.092581602],"iteration":966,"passed_time":0.7727047667,"remaining_time":0.02636944912},
{"learn":[3.091694202],"iteration":967,"passed_time":0.7733854808,"remaining_time":0.02556646218},
{"learn":[3.090298312],"iteration":968,"passed_time":0.7741206999,"remaining_time":0.02476547131},
{"learn":[3.090020107],"iteration":969,"passed_time":0.7747310875,"remaining_time":0.02396075528},
{"learn":[3.088949869],"iteration":970,"passed_time":0.7753471768,"remaining_time":0.02315660981},
{"learn":[3.086700204],"iteration":971,"passed_time":0.7760726907,"remaining_time":0.02235600344},
{"learn":[3.086584317],"iteration":972,"passed_time":0.7767072225,"remaining_time":0.02155302673},
{"learn":[3.084850742],"iteration":973,"passed_time":0.7773348023,"remaining_time":0.02075021033},
{"learn":[3.084239948],"iteration":974,"passed_time":0.7779130037,"remaining_time":0.01994648728},
{"learn":[3.082561673],"iteration":975,"passed_time":0.7785894502,"remaining_time":0.01914564222},
{"learn":[3.07991814],"iteration":976,"passed_time":0.7794016869,"remaining_time":0.01834824851},
{"learn":[3.079350277],"iteration":977,"passed_time":0.7800627912,"remaining_time":0.01754742475},
{"learn":[3.077637462],"iteration":978,"passed_time":0.7805903725,"remaining_time":0.01674402229},
{"learn":[3.076733301],"iteration":979,"passed_time":0.7811164799,"remaining_time":0.01594115265},
{"learn":[3.07594065],"iteration":980,"passed_time":0.7817027145,"remaining_time":0.0151400118},
{"learn":[3.072594655],"iteration":981,"passed_time":0.7823437266,"remaining_time":0.01434031271},
{"learn":[3.071977674],"iteration":982,"passed_time":0.782941081,"remaining_time":0.01354018146},
{"learn":[3.069532634],"iteration":983,"passed_time":0.783490992,"remaining_time":0.01273969093},
{"learn":[3.068870784],"iteration":984,"passed_time":0.7840343116,"remaining_time":0.01193960881},
{"learn":[3.068801463],"iteration":985,"passed_time":0.7845339519,"remaining_time":0.01113942731},
{"learn":[3.067433249],"iteration":986,"passed_time":0.7850504522,"remaining_time":0.01034007688},
{"learn":[3.065611456],"iteration":987,"passed_time":0.7856629639,"remaining_time":0.009542465148},
{"learn":[3.063039162],"iteration":988,"passed_time":0.7861834914,"remaining_time":0.008744204656},
{"learn":[3.06177873],"iteration":989,"passed_time":0.7867743945,"remaining_time":0.007947216107},
{"learn":[3.061689148],"iteration":990,"passed_time":0.7873837819,"remaining_time":0.007150811339},
{"learn":[3.058984039],"iteration":991,"passed_time":0.7880433365,"remaining_time":0.006355188197},
{"learn":[3.057492984],"iteration":992,"passed_time":0.7886139532,"remaining_time":0.005559212157},
{"learn":[3.057290731],"iteration":993,"passed_time":0.7892167227,"remaining_time":0.004763883638},
{"learn":[3.056068348],"iteration":994,"passed_time":0.7898210285,"remaining_time":0.003968949892},
{"learn":[3.054987307],"iteration":995,"passed_time":0.7904362848,"remaining_time":0.003174442911},
{"learn":[3.054200234],"iteration":996,"passed_time":0.7910743216,"remaining_time":0.002380364057},
{"learn":[3.052732869],"iteration":997,"passed_time":0.791732284,"remaining_time":0.001586637844},
{"learn":[3.051787862],"iteration":998,"passed_time":0.7924442225,"remaining_time":0.00079323746},
{"learn":[3.051366222],"iteration":999,"passed_time":0.7931156899,"remaining_time":0}
]}